Workbook

Sheet KPI Dashboard
A1: Finance Operations KPI Dashboard
A2: Sample workbook (40 stratified merchants) - live formulas, recalculates if source sheets change
A4: Total Expected Revenue | B4: =SUM(tblInvoices[expected_fee])
A5: Total Billed Revenue | B5: =SUM(tblInvoices[billed_fee])
A6: Billing Accuracy % | B6: =ROUND(100*COUNTIF('Invoice Validation'!H4:H1000,"Correct")/COUNTA(tblInvoices[invoice_id]),2)
A7: Total Collected (Payments, Success) | B7: =SUMIFS(tblPayments[payment_amount],tblPayments[payment_status],"Success")
A8: Revenue Realization % | B8: =ROUND(100*B7/B5,2)
A9: Total Outstanding AR | B9: =SUM('AR Aging'!G5:G1000)
A10: Invoices Analyzed | B10: =COUNTA(tblInvoices[invoice_id])
A11: Payments Analyzed | B11: =COUNTA(tblPayments[payment_id])
A12: Merchants in Sample | B12: =COUNTA(tblMerchants[merchant_id])
A14: See other sheets for full detail: Invoices, Payments, Invoice Validation, AR Aging, Collections, Revenue Reconciliation, Monthly MIS.

Sheet Merchants
A1: Merchant Reference (lookup source for XLOOKUP formulas on other sheets)
A3: merchant_id | B3: merchant_name | C3: industry | D3: merchant_segment | E3: city | F3: state | G3: country | H3: onboarding_date | I3: account_manager | J3: pricing_plan | K3: contract_start_date | L3: contract_end_date | M3: agreed_fee_percent | N3: monthly_subscription_fee | O3: payment_terms_days | P3: merchant_status
A4: MER00048 | B4: Martin, Rose and Obrien | C4: Sports & Fitness | D4: Long-tail | E4: Surat | F4: Gujarat | G4: India | H4: 45535 | I4: Pooja Agarwal | J4: Standard | K4: 45535 | M4: 3.41 | N4: 0 | O4: 15 | P4: Active
A5: MER00055 | B5: Jones Inc | C5: Jewellery & Accessories | D5: SMB | E5: Nagpur | F5: Maharashtra | G5: India | H5: 45523 | I5: Priya Nair | J5: Standard | K5: 45523 | M5: 2.69 | N5: 0 | O5: 30 | P5: Active
A6: MER00074 | B6: Stanley, Tucker and Lee | C6: Electronics | D6: Mid-Market | E6: Chandigarh | F6: Chandigarh | G6: India | H6: 45537 | I6: Tanvi Shah | J6: Custom | K6: 45537 | M6: 1.92 | N6: 9999 | O6: 45 | P6: Active
A7: MER00077 | B7: Woods, Calhoun and Schmidt | C7: Fashion & Apparel | D7: SMB | E7: Nagpur | F7: Maharashtra | G7: India | H7: 45522 | I7: Divya Menon | J7: Enterprise | K7: 45522 | M7: 2.22 | N7: 4999 | O7: 15 | P7: Active
A8: MER00139 | B8: Harvey, Davis and Crane | C8: Health & Wellness | D8: Enterprise | E8: Pune | F8: Maharashtra | G8: India | H8: 45525 | I8: Aditya Bose | J8: Enterprise | K8: 45525 | M8: 2 | N8: 4999 | O8: 60 | P8: Active
A9: MER00140 | B9: Chambers and Sons | C9: Home & Living | D9: SMB | E9: Gurugram | F9: Haryana | G9: India | H9: 45511 | I9: Arjun Reddy | J9: Standard | K9: 45511 | M9: 2.57 | N9: 0 | O9: 15 | P9: Active
A10: MER00156 | B10: Hill Inc | C10: Health & Wellness | D10: Long-tail | E10: Noida | F10: Uttar Pradesh | G10: India | H10: 45685 | I10: Divya Menon | J10: Standard | K10: 45685 | M10: 3.25 | N10: 0 | O10: 30 | P10: Active
A11: MER00184 | B11: Higgins, Strickland and Martin | C11: Beauty & Personal Care | D11: Mid-Market | E11: Kochi | F11: Kerala | G11: India | H11: 45518 | I11: Karan Malhotra | J11: Standard | K11: 45518 | L11: 45887 | M11: 2.13 | N11: 0 | O11: 30 | P11: Churned
A12: MER00189 | B12: Garcia LLC | C12: Health & Wellness | D12: Long-tail | E12: Nagpur | F12: Maharashtra | G12: India | H12: 45515 | I12: Arjun Reddy | J12: Standard | K12: 45515 | M12: 2.69 | N12: 0 | O12: 15 | P12: Active
A13: MER00203 | B13: Peterson-Beard | C13: Electronics | D13: SMB | E13: Coimbatore | F13: Tamil Nadu | G13: India | H13: 45521 | I13: Pooja Agarwal | J13: Growth | K13: 45521 | M13: 2.69 | N13: 999 | O13: 30 | P13: Active
A14: MER00346 | B14: Zhang PLC | C14: Fashion & Apparel | D14: Long-tail | E14: Gurugram | F14: Haryana | G14: India | H14: 45539 | I14: Kabir Chatterjee | J14: Growth | K14: 45539 | M14: 3.34 | N14: 999 | O14: 15 | P14: Active
A15: MER00347 | B15: Jones PLC | C15: Jewellery & Accessories | D15: SMB | E15: Noida | F15: Uttar Pradesh | G15: India | H15: 46172 | I15: Arjun Reddy | J15: Growth | K15: 46172 | M15: 2.4 | N15: 999 | O15: 30 | P15: Active
A16: MER00355 | B16: Fisher, Wilson and Brown | C16: Home & Living | D16: Long-tail | E16: Noida | F16: Uttar Pradesh | G16: India | H16: 45526 | I16: Meera Pillai | J16: Standard | K16: 45526 | M16: 2.51 | N16: 0 | O16: 15 | P16: Active
A17: MER00381 | B17: Richardson, Farmer and Andrews | C17: Food & Beverage | D17: SMB | E17: Gurugram | F17: Haryana | G17: India | H17: 45527 | I17: Sneha Iyer | J17: Growth | K17: 45527 | M17: 2.71 | N17: 999 | O17: 15 | P17: Active
A18: MER00386 | B18: Kane PLC | C18: Sports & Fitness | D18: SMB | E18: Ahmedabad | F18: Gujarat | G18: India | H18: 45792 | I18: Priya Nair | J18: Growth | K18: 45792 | M18: 2.35 | N18: 999 | O18: 15 | P18: Active
A19: MER00436 | B19: Cox LLC | C19: Home & Living | D19: Enterprise | E19: Chandigarh | F19: Chandigarh | G19: India | H19: 45535 | I19: Ananya Sharma | J19: Custom | K19: 45535 | M19: 1.96 | N19: 9999 | O19: 45 | P19: Active
A20: MER00457 | B20: Bishop-Goodwin | C20: Electronics | D20: Long-tail | E20: Chennai | F20: Tamil Nadu | G20: India | H20: 45518 | I20: Divya Menon | J20: Growth | K20: 45518 | M20: 3.11 | N20: 999 | O20: 15 | P20: Active
A21: MER00480 | B21: Barnes PLC | C21: Electronics | D21: SMB | E21: Nagpur | F21: Maharashtra | G21: India | H21: 45511 | I21: Priya Nair | J21: Standard | K21: 45511 | M21: 2.61 | N21: 0 | O21: 30 | P21: Active
A22: MER00484 | B22: Mendez and Sons | C22: Sports & Fitness | D22: Long-tail | E22: Surat | F22: Gujarat | G22: India | H22: 45529 | I22: Siddharth Joshi | J22: Standard | K22: 45529 | M22: 3.21 | N22: 0 | O22: 30 | P22: Active
A23: MER00502 | B23: Paul-Kline | C23: Food & Beverage | D23: SMB | E23: Surat | F23: Gujarat | G23: India | H23: 45528 | I23: Priya Nair | J23: Growth | K23: 45528 | M23: 2.7 | N23: 999 | O23: 15 | P23: Active
... A43: MER00902 | B43: Griffith, Mitchell and Pugh | C43: Fashion & Apparel | D43: Mid-Market | E43: Chandigarh | F43: Chandigarh | G43: India | H43: 45529 | I43: Pooja Agarwal | J43: Growth | K43: 45529 | M43: 1.86 | N43: 999 | O43: 30 | P43: Active

Sheet Raw Transactions
A1: Raw Transactions (sampled: 2,500 of the full dataset for these merchants)
A3: transaction_id | B3: merchant_id | C3: transaction_date | D3: order_id | E3: transaction_amount | F3: transaction_fee_percent | G3: expected_platform_fee | H3: payment_method | I3: payment_status | J3: order_status | K3: refund_amount | L3: discount_amount | M3: currency | N3: created_timestamp
A4: TXN00005842 | B4: MER00048 | C4: 45529 | D4: ORD00005842 | E4: 1086.34 | F4: 2.5 | G4: 27.16 | H4: NetBanking | I4: Success | J4: Delivered | K4: 0 | L4: 0 | M4: INR | N4: 2024-08-25 11:40:02
A5: TXN00012021 | B5: MER00048 | C5: 45551 | D5: ORD00012021 | E5: 813.81 | F5: 3.41 | G5: 27.75 | H5: UPI | I5: Success | J5: Delivered | K5: 0 | L5: 0 | M5: INR | N5: 2024-09-16 16:50:30
A6: TXN00027065 | B6: MER00048 | C6: 45594 | D6: ORD00027065 | E6: 1613.07 | F6: 3.41 | G6: 55.01 | H6: Card | I6: Success | J6: Returned | K6: 880.93 | L6: 0 | M6: INR | N6: 2024-10-29 04:27:47
A7: TXN00030133 | B7: MER00048 | C7: 45601 | D7: ORD00030133 | E7: 3904.39 | F7: 3.41 | G7: 133.14 | H7: UPI | I7: Success | J7: Delivered | K7: 0 | L7: 0 | M7: INR | N7: 2024-11-05 14:31:54
A8: TXN00069246 | B8: MER00048 | C8: 45707 | D8: ORD00069246 | E8: 2134.51 | F8: 3.41 | G8: 72.79 | H8: UPI | I8: Pending | J8: Processing | K8: 0 | L8: 205.69 | M8: INR | N8: 2025-02-19 20:19:36
A9: TXN00074371 | B9: MER00048 | C9: 45723 | D9: ORD00074371 | E9: 1437.74 | F9: 3.41 | G9: 49.03 | H9: Card | I9: Success | J9: Delivered | K9: 0 | L9: 0 | M9: INR | N9: 2025-03-07 21:16:56
A10: TXN00093558 | B10: MER00048 | C10: 45782 | D10: ORD00093558 | E10: 1275.62 | F10: 3.41 | G10: 43.5 | H10: UPI | I10: Success | J10: Cancelled | K10: 1269.78 | L10: 0 | M10: INR | N10: 2025-05-05 23:19:04
A11: TXN00098341 | B11: MER00048 | C11: 45797 | D11: ORD00098341 | E11: 2331.89 | F11: 3.41 | G11: 79.52 | H11: UPI | I11: Success | J11: Returned | K11: 1784.53 | L11: 378.59 | M11: INR | N11: 2025-05-20 03:19:12
A12: TXN00130791 | B12: MER00048 | C12: 45894 | D12: ORD00130791 | E12: 2316.69 | F12: 3.41 | G12: 79 | H12: UPI | I12: Success | J12: Delivered | K12: 0 | L12: 0 | M12: INR | N12: 2025-08-25 10:21:02
A13: TXN00136801 | B13: MER00048 | C13: 45911 | D13: ORD00136801 | E13: 2035.75 | F13: 3.41 | G13: 69.42 | H13: Card | I13: Success | J13: Delivered | K13: 0 | L13: 0 | M13: INR | N13: 2025-09-11 22:27:17
A14: TXN00188216 | B14: MER00048 | C14: 46027 | D14: ORD00188216 | E14: 622.62 | F14: 3.41 | G14: 21.23 | H14: Card | I14: Success | J14: Delivered | K14: 0 | L14: 0 | M14: INR | N14: 2026-01-05 16:55:59
A15: TXN00206757 | B15: MER00048 | C15: 46069 | D15: ORD00206757 | E15: 844.84 | F15: 3.41 | G15: 28.81 | H15: Card | I15: Success | J15: Delivered | K15: 0 | L15: 0 | M15: INR | N15: 2026-02-16 22:10:23
... A2503: TXN00263343 | B2503: MER00902 | C2503: 46216 | D2503: ORD00263343 | E2503: 2513.65 | F2503: 1.86 | G2503: 46.75 | H2503: UPI | I2503: Success | J2503: Delivered | K2503: 0 | L2503: 0 | M2503: INR | N2503: 2026-07-13 16:35:18

Sheet Invoices
A1: Invoices
A3: invoice_id | B3: merchant_id | C3: billing_period_start | D3: billing_period_end | E3: invoice_date | F3: due_date | G3: subtotal | H3: discount | I3: taxable_amount | J3: tax_rate | K3: tax_amount | L3: total_invoice_amount | M3: currency | N3: invoice_status | O3: payment_status | P3: expected_fee | Q3: billed_fee | R3: invoice_error_flag
A4: INV0000956 | B4: MER00048 | C4: 2024-08-01 | D4: 2024-08-31 | E4: 45537 | F4: 45552 | G4: 80.15 | H4: 0 | I4: 80.15 | J4: 0.18 | K4: 14.43 | L4: 94.58 | M4: INR | N4: Paid | O4: Paid | P4: 80.15 | Q4: 80.15 | R4: FALSE
A5: INV0000957 | B5: MER00048 | C5: 2024-09-01 | D5: 2024-09-30 | E5: 45567 | F5: 45582 | G5: 326.04 | H5: 0 | I5: 326.04 | J5: 0.18 | K5: 58.69 | L5: 384.73 | M5: INR | N5: Paid | O5: Paid | P5: 326.04 | Q5: 326.04 | R5: FALSE
A6: INV0000958 | B6: MER00048 | C6: 2024-10-01 | D6: 2024-10-31 | E6: 45598 | F6: 45613 | G6: 258.85 | H6: 0 | I6: 258.85 | J6: 0.18 | K6: 46.59 | L6: 305.44 | M6: INR | N6: Paid | O6: Paid | P6: 258.85 | Q6: 258.85 | R6: FALSE
A7: INV0000959 | B7: MER00048 | C7: 2024-11-01 | D7: 2024-11-30 | E7: 45628 | F7: 45643 | G7: 511.05 | H7: 0 | I7: 511.05 | J7: 0.18 | K7: 91.99 | L7: 603.04 | M7: INR | N7: Paid | O7: Paid | P7: 511.05 | Q7: 511.05 | R7: FALSE
A8: INV0000960 | B8: MER00048 | C8: 2024-12-01 | D8: 2024-12-31 | E8: 45659 | F8: 45674 | G8: 55.69 | H8: 0 | I8: 55.69 | J8: 0.18 | K8: 10.02 | L8: 65.71 | M8: INR | N8: Paid | O8: Paid | P8: 67.41 | Q8: 55.69 | R8: TRUE
A9: INV0000961 | B9: MER00048 | C9: 2025-01-01 | D9: 2025-01-31 | E9: 45690 | F9: 45705 | G9: 160.14 | H9: 12.49 | I9: 147.65 | J9: 0.18 | K9: 26.58 | L9: 174.23 | M9: INR | N9: Paid | O9: Paid | P9: 160.14 | Q9: 160.14 | R9: FALSE
A10: INV0000962 | B10: MER00048 | C10: 2025-02-01 | D10: 2025-02-28 | E10: 45718 | F10: 45733 | G10: 162.38 | H10: 0 | I10: 162.38 | J10: 0.18 | K10: 29.23 | L10: 191.61 | M10: INR | N10: Paid | O10: Paid | P10: 162.38 | Q10: 162.38 | R10: FALSE
A11: INV0000963 | B11: MER00048 | C11: 2025-03-01 | D11: 2025-03-31 | E11: 45749 | F11: 45764 | G11: 101.64 | H11: 0 | I11: 101.64 | J11: 0.18 | K11: 18.3 | L11: 119.94 | M11: INR | N11: Paid | O11: Paid | P11: 101.64 | Q11: 101.64 | R11: FALSE
A12: INV0000964 | B12: MER00048 | C12: 2025-04-01 | D12: 2025-04-30 | E12: 45779 | F12: 45794 | G12: 315.45 | H12: 43.53 | I12: 271.92 | J12: 0.18 | K12: 48.95 | L12: 320.87 | M12: INR | N12: Paid | O12: Paid | P12: 315.45 | Q12: 315.45 | R12: FALSE
A13: INV0000965 | B13: MER00048 | C13: 2025-05-01 | D13: 2025-05-31 | E13: 45810 | F13: 45825 | G13: 287.68 | H13: 0 | I13: 287.68 | J13: 0.18 | K13: 51.78 | L13: 339.46 | M13: INR | N13: Paid | O13: Paid | P13: 287.68 | Q13: 287.68 | R13: FALSE
A14: INV0000966 | B14: MER00048 | C14: 2025-07-01 | D14: 2025-07-31 | E14: 45871 | F14: 45886 | G14: 168.49 | H14: 0 | I14: 168.49 | J14: 0.18 | K14: 30.33 | L14: 198.82 | M14: INR | N14: Paid | O14: Paid | P14: 168.49 | Q14: 168.49 | R14: FALSE
A15: INV0000967 | B15: MER00048 | C15: 2025-08-01 | D15: 2025-08-31 | E15: 45902 | F15: 45917 | G15: 166.18 | H15: 19.78 | I15: 146.4 | J15: 0.18 | K15: 26.35 | L15: 172.75 | M15: INR | N15: Paid | O15: Paid | P15: 166.18 | Q15: 166.18 | R15: FALSE
... A898: INV0019140 | B898: MER00902 | C898: 2026-07-01 | D898: 2026-07-31 | E898: 46236 | F898: 46266 | G898: 530.76 | H898: 0 | I898: 530.76 | J898: 0.18 | K898: 95.54 | L898: 626.3 | M898: INR | N898: Paid | O898: Paid | P898: 530.76 | Q898: 530.76 | R898: FALSE

Sheet Payments
A1: Payments
A3: payment_id | B3: invoice_id | C3: merchant_id | D3: payment_date | E3: payment_amount | F3: payment_method | G3: payment_reference | H3: payment_status | I3: bank_reference | J3: settlement_date
A4: PAY0000165 | B4: INV0000956 | C4: MER00048 | D4: 45549 | E4: 94.58 | F4: Card | G4: PAYMKP6KQR24E | H4: Success | I4: BNKMQ2KPJLA326D | J4: 45550
A5: PAY0000166 | B5: INV0000957 | C5: MER00048 | D5: 45579 | E5: 384.73 | F5: UPI | G5: PAYG38QBVMBUN | H5: Success | I5: BNK8G4PL86ZH5QB | J5: 45582
A6: PAY0000167 | B6: INV0000958 | C6: MER00048 | D6: 45608 | E6: 305.44 | F6: UPI | G6: PAYX4QSV4PCFH | H6: Success | I6: BNKJBTGPFPUWDWP | J6: 45609
A7: PAY0000168 | B7: INV0000959 | C7: MER00048 | D7: 45635 | E7: 603.04 | F7: Card | G7: PAYLMV9CN64BX | H7: Success | I7: BNKRLQMHTYN84L3 | J7: 45636
A8: PAY0000169 | B8: INV0000960 | C8: MER00048 | D8: 45675 | E8: 65.71 | F8: Card | G8: PAYQMR34A2NF6 | H8: Success | I8: BNKNJ695DMUQW8S | J8: 45677
A9: PAY0000170 | B9: INV0000962 | C9: MER00048 | D9: 45734 | E9: 191.61 | F9: UPI | G9: PAYXNTPE9KLN5 | H9: Success | I9: BNK8GAARTLR8H76 | J9: 45735
A10: PAY0000171 | B10: INV0000963 | C10: MER00048 | D10: 45764 | E10: 119.94 | F10: UPI | G10: PAYRBFLRYWH7T | H10: Success | I10: BNKA8VLKDZLQSZC | J10: 45766
A11: PAY0000172 | B11: INV0000964 | C11: MER00048 | D11: 45789 | E11: 320.87 | F11: UPI | G11: PAYKVUZN2JTAE | H11: Success | I11: BNK48JEDJKBTVDZ | J11: 45791
A12: PAY0000173 | B12: INV0000965 | C12: MER00048 | D12: 45825 | E12: 339.46 | F12: UPI | G12: PAYD9KANKTU6U | H12: Success | I12: BNK39DUPLVEV8C4 | J12: 45826
A13: PAY0000174 | B13: INV0000966 | C13: MER00048 | D13: 45886 | E13: 198.82 | F13: Card | G13: PAY6R8VLDQWAH | H13: Success | I13: BNKB25HV2UNXHX9 | J13: 45889
A14: PAY0000175 | B14: INV0000967 | C14: MER00048 | D14: 45915 | E14: 172.75 | F14: UPI | G14: PAY9FGL2LWD4R | H14: Success | I14: BNKYY5J537M8D2B | J14: 45917
A15: PAY0000176 | B15: INV0000968 | C15: MER00048 | D15: 45939 | E15: 345.26 | F15: UPI | G15: PAY9E2DJMHQ39 | H15: Success | I15: BNKY9LYTPNAG6UZ | J15: 45942
... A54: PAY0001850 | B54: INV0008129 | C54: MER00386 | D54: 46003 | E54: 582.74 | F54: UPI | G54: PAYC6M6T355MZ | H54: Success | I54: BNK3M6TDTFC74JQ | J54: 46004
A55: PAY0001851 | B55: INV0008130 | C55: MER00386 | D55: 46034 | E55: 703.17 | F55: UPI | G55: PAY43DE56TVKJ | H55: Failed | I55: BNKNXALCXR45KYK
A56: PAY0001852 | B56: INV0008131 | C56: MER00386 | D56: 46093 | E56: 673.14 | F56: UPI | G56: PAYZT6TXHWX6V | H56: Success | I56: BNKD9LZ2KUHY3EP | J56: 46096
A57: PAY0001853 | B57: INV0008132 | C57: MER00386 | D57: 46132 | E57: 772.69 | F57: UPI | G57: PAYECRJR8FTMU | H57: Success | I57: BNK6KX95VH4J3W5 | J57: 46133
A58: PAY0001854 | B58: INV0008133 | C58: MER00386 | D58: 46160 | E58: 519.7 | F58: Card | G58: PAY8UGMCRGGR2 | H58: Success | I58: BNK3P6MUZXEGY2K | J58: 46163
A59: PAY0001855 | B59: INV0008134 | C59: MER00386 | D59: 46190 | E59: 367.03 | F59: NetBanking | G59: PAYCCH8WFSZFN | H59: Success | I59: BNK25AVC3UL49MG | J59: 46193
A60: PAY0001856 | B60: INV0008135 | C60: MER00386 | D60: 46214 | E60: 494.34 | F60: UPI | G60: PAY6S5KRUJ9WV | H60: Success | I60: BNKGBTEKY44W6EJ | J60: 46216
A61: PAY0001857 | B61: INV0008136 | C61: MER00386 | D61: 46245 | E61: 586.4 | F61: UPI | G61: PAYUPFED4ZM3U | H61: Success | I61: BNKQHKB4KKMYNC2 | J61: 46246
A62: PAY0002060 | B62: INV0009199 | C62: MER00436 | D62: 45582 | E62: 3151.01 | F62: UPI | G62: PAYPJREJCG472 | H62: Success | I62: BNKFPU48769M2CR | J62: 45585
A63: PAY0002061 | B63: INV0009200 | C63: MER00436 | D63: 45611 | E63: 2210.45 | F63: Card | G63: PAYJRJ27KRFWQ | H63: Success | I63: BNK982SDYU5GAB5 | J63: 45614
A64: PAY0002062 | B64: INV0009201 | C64: MER00436 | D64: 45640 | E64: 3622.79 | F64: Card | G64: PAY2S4K5Y53PF | H64: Success | I64: BNKL8WFY7G48SAN | J64: 45643
A65: PAY0002063 | B65: INV0009202 | C65: MER00436 | D65: 45666 | E65: 2817.46 | F65: UPI | G65: PAYUMUGG744GT | H65: Success | I65: BNKH3B32GVSGXGY | J65: 45669
A66: PAY0002064 | B66: INV0009203 | C66: MER00436 | D66: 45706 | E66: 2967.03 | F66: UPI | G66: PAYFLJR4AGGUA | H66: Success | I66: BNKZ4PGG3UBTYEY | J66: 45708
A67: PAY0002065 | B67: INV0009204 | C67: MER00436 | D67: 45731 | E67: 3438.18 | F67: UPI | G67: PAYPG5RE86663 | H67: Success | I67: BNKDFNTYB4EP3DX | J67: 45733
... A209: PAY0004402 | B209: INV0018134 | C209: MER00856 | D209: 46052 | E209: 283.88 | F209: NetBanking | G209: PAYTPXQMTKCWN | H209: Success | I209: BNKP8ZN3SRS2J9N | J209: 46054
A210: PAY0004403 | B210: INV0018135 | C210: MER00856 | D210: 46082 | E210: 190.36 | F210: Card | G210: PAYHQ6U6D9YUS | H210: Failed | I210: BNKH4KYR35GZ2NW
A211: PAY0004404 | B211: INV0018136 | C211: MER00856 | D211: 46110 | E211: 167.93 | F211: Card | G211: PAYUSKHQEWFV5 | H211: Success | I211: BNKQZG7LAWWHRVV | J211: 46111
A212: PAY0004405 | B212: INV0018137 | C212: MER00856 | D212: 46144 | E212: 105.43 | F212: UPI | G212: PAYU6GP5KRHTW | H212: Success | I212: BNKK32SFKE6TAQ6 | J212: 46146
A213: PAY0004406 | B213: INV0018138 | C213: MER00856 | D213: 46173 | E213: 90.49 | F213: UPI | G213: PAY9MTSAVML6N | H213: Success | I213: BNKLMZYCP3MAGCH | J213: 46174
A214: PAY0004407 | B214: INV0018140 | C214: MER00856 | D214: 46235 | E214: 125.25 | F214: UPI | G214: PAYBHHM474TVE | H214: Success | I214: BNKDRNE3E252GJ6 | J214: 46238
A215: PAY0004408 | B215: INV0018141 | C215: MER00856 | D215: 46263 | E215: 185.17 | F215: Card | G215: PAYXHYX49Z8HC | H215: Success | I215: BNKT4926YA6UJML | J215: 46266
A216: PAY0004433 | B216: INV0018395 | C216: MER00870 | D216: 45593 | E216: 246.95 | F216: UPI | G216: PAY43H5LPK56D | H216: Success | I216: BNKLMMUDEFE3X5F | J216: 45595
A217: PAY0004434 | B217: INV0018396 | C217: MER00870 | D217: 45628 | E217: 209.95 | F217: UPI | G217: PAY9KNLA67CAF | H217: Success | I217: BNKFK26RUQ3LWLE | J217: 45631
A218: PAY0004435 | B218: INV0018397 | C218: MER00870 | D218: 45660 | E218: 94.88 | F218: UPI | G218: PAYKGHJHVUK8N | H218: Success | I218: BNKQ2VBRW4SED5P | J218: 45661
A219: PAY0004436 | B219: INV0018398 | C219: MER00870 | D219: 45684 | E219: 69.23 | F219: COD | G219: PAYD8ZSDF3EK4 | H219: Success | I219: BNKCJ5WWL4Y2XGC | J219: 45686
A220: PAY0004437 | B220: INV0018399 | C220: MER00870 | D220: 45721 | E220: 545.94 | F220: UPI | G220: PAYR8LE8AATRD | H220: Success | I220: BNK9P7ALN9EM7XJ | J220: 45722
A221: PAY0004438 | B221: INV0018400 | C221: MER00870 | D221: 45743 | E221: 214.19 | F221: UPI | G221: PAYWG8LTR2NLX | H221: Success | I221: BNKV4VP99R36GHG | J221: 45746
A222: PAY0004439 | B222: INV0018401 | C222: MER00870 | D222: 45776 | E222: 142.12 | F222: UPI | G222: PAYATMZ4MK5TV | H222: Failed | I222: BNK23HZ7W7YCTXL
A223: PAY0004440 | B223: INV0018402 | C223: MER00870 | D223: 45837 | E223: 252 | F223: Card | G223: PAYWBJHZRCM2R | H223: Success | I223: BNKHCSXWG9RDQFZ | J223: 45840
A224: PAY0004441 | B224: INV0018403 | C224: MER00870 | D224: 45869 | E224: 282 | F224: NetBanking | G224: PAY7DQXR92FEB | H224: Success | I224: BNK5TGPM8FUQ6KP | J224: 45870
A225: PAY0004442 | B225: INV0018404 | C225: MER00870 | D225: 45898 | E225: 41.28 | F225: NetBanking | G225: PAY7XRABGANJ8 | H225: Success | I225: BNKP4JPJR7CNHQH | J225: 45901
A226: PAY0004443 | B226: INV0018405 | C226: MER00870 | D226: 45933 | E226: 264.28 | F226: COD | G226: PAYD372VDQQKJ | H226: Success | I226: BNKSQW87F4MB3GE | J226: 45936
A227: PAY0004444 | B227: INV0018406 | C227: MER00870 | D227: 45957 | E227: 111.14 | F227: Wallet | G227: PAY23E459BQGU | H227: Success | I227: BNKKE6BE3Q2QV4J | J227: 45958
A228: PAY0004445 | B228: INV0018407 | C228: MER00870 | D228: 45990 | E228: 95.3 | F228: NetBanking | G228: PAY65PLRXLT6M | H228: Success | I228: BNKM8X4AF6XSME8 | J228: 45992
A229: PAY0004446 | B229: INV0018409 | C229: MER00870 | D229: 46057 | E229: 95.16 | F229: UPI | G229: PAYB5H29TZT73 | H229: Success | I229: BNKRHU3ZZLXQHCW | J229: 46058
A230: PAY0004447 | B230: INV0018410 | C230: MER00870 | D230: 46088 | E230: 166.82 | F230: Card | G230: PAY867L4SYFPM | H230: Success | I230: BNKFWBBKFH6MCPX | J230: 46090
A231: PAY0004448 | B231: INV0018411 | C231: MER00870 | D231: 46144 | E231: 211.76 | F231: Wallet | G231: PAYFHY568EUHT | H231: Success | I231: BNKSE4HHQDS8BD9 | J231: 46147
A232: PAY0004449 | B232: INV0018412 | C232: MER00870 | D232: 46164 | E232: 302.3 | F232: Wallet | G232: PAYGZBG9FHJL8 | H232: Success | I232: BNKRZBYE683KT94 | J232: 46167
A233: PAY0004450 | B233: INV0018413 | C233: MER00870 | D233: 46205 | E233: 510.85 | F233: Card | G233: PAYL5CE5FURK8 | H233: Success | I233: BNKHGTB3HTVBT5K | J233: 46206
A234: PAY0004451 | B234: INV0018414 | C234: MER00870 | D234: 46236 | E234: 189.2 | F234: Card | G234: PAYQTTEUVETDP | H234: Success | I234: BNK54LKJ79LG9HH | J234: 46237
... A257: PAY0005815 | B257: INV0001547 | C257: MER00074 | D257: 45832 | E257: 1100.55 | F257: Card | G257: PAYYWX36LXL8K | H257: Success | I257: BNKUAYFSRNAJWRB | J257: 45834
A258: PAY0005816 | B258: INV0001550 | C258: MER00074 | D258: 45921 | E258: 1699.74 | F258: UPI | G258: PAY6VT3JVYS5W | H258: Failed | I258: BNKY38JF98QPDJV
A259: PAY0005817 | B259: INV0001551 | C259: MER00074 | D259: 45940 | E259: 1764.25 | F259: UPI | G259: PAYVKSJGMGC4X | H259: Success | I259: BNKJC7B9LE4AE4H | J259: 45941
A260: PAY0005818 | B260: INV0001552 | C260: MER00074 | D260: 45988 | E260: 1022 | F260: Wallet | G260: PAYKMHS4EDBZS | H260: Success | I260: BNKCY38A8WTYCBR | J260: 45989
A261: PAY0005819 | B261: INV0001553 | C261: MER00074 | D261: 46007 | E261: 2817.5 | F261: Card | G261: PAYY2CRAAYJ7C | H261: Success | I261: BNKJMJPXLLVW79M | J261: 46008
A262: PAY0005820 | B262: INV0001554 | C262: MER00074 | D262: 46037 | E262: 2890.03 | F262: UPI | G262: PAYZVK7L2SF6Q | H262: Success | I262: BNKQCZS7Z2AVB32 | J262: 46039
A263: PAY0005821 | B263: INV0001555 | C263: MER00074 | D263: 46083 | E263: 1414.81 | F263: UPI | G263: PAYRN3ABXS8XR | H263: Success | I263: BNK5GCB5HZSKCK7 | J263: 46085
A264: PAY0005822 | B264: INV0001556 | C264: MER00074 | D264: 46105 | E264: 3349.1 | F264: UPI | G264: PAY3THRUGWSYG | H264: Success | I264: BNKEWAA92STS7UD | J264: 46108
A265: PAY0005823 | B265: INV0001558 | C265: MER00074 | D265: 46170 | E265: 1990.15 | F265: UPI | G265: PAYD9KL6A54J7 | H265: Success | I265: BNKKWQCHQZA5VEC | J265: 46173
A266: PAY0005824 | B266: INV0001559 | C266: MER00074 | D266: 46202 | E266: 2655.76 | F266: Card | G266: PAY9Z3QBE7L3F | H266: Success | I266: BNKRL7STLMK7PQB | J266: 46205
A267: PAY0005825 | B267: INV0001560 | C267: MER00074 | D267: 46214 | E267: 1147.68 | F267: UPI | G267: PAYM7KSRGQQEG | H267: Success | I267: BNKSU67C7Z9MSYY | J267: 46215
A268: PAY0007676 | B268: INV0008006 | C268: MER00381 | D268: 45556 | E268: 97.03 | F268: NetBanking | G268: PAYX6BNTZNDSL | H268: Success | I268: BNK8VN6EMLVZEBN | J268: 45558
A269: PAY0007677 | B269: INV0008007 | C269: MER00381 | D269: 45574 | E269: 61.64 | F269: UPI | G269: PAYWZ857ZBERZ | H269: Success | I269: BNKXKT9SXCA26GF | J269: 45577
A270: PAY0007678 | B270: INV0008008 | C270: MER00381 | D270: 45613 | E270: 314.92 | F270: Wallet | G270: PAYDAFHQKWRM6 | H270: Success | I270: BNKVLQ63TPBDDJ5 | J270: 45615
... A274: PAY0007682 | B274: INV0008014 | C274: MER00381 | D274: 45803 | E274: 174.35 | F274: UPI | G274: PAY2SXKKLCPTT | H274: Success | I274: BNKALCGMNCYXZHL | J274: 45805
A275: PAY0007683 | B275: INV0008015 | C275: MER00381 | D275: 45834 | E275: 210.35 | F275: UPI | G275: PAYRRS3LW8X6U | H275: Failed | I275: BNKVFUAL9QKQVVN
A276: PAY0007684 | B276: INV0008016 | C276: MER00381 | D276: 45866 | E276: 97.17 | F276: Card | G276: PAYYCUTPF563W | H276: Success | I276: BNKLMQFFJXUXCTJ | J276: 45868
A277: PAY0007685 | B277: INV0008017 | C277: MER00381 | D277: 45884 | E277: 195.92 | F277: UPI | G277: PAYUDHKCGVCLF | H277: Success | I277: BNKFQXKWD8AH7HC | J277: 45885
A278: PAY0007686 | B278: INV0008018 | C278: MER00381 | D278: 45928 | E278: 153.69 | F278: UPI | G278: PAYJUUCKXWGSL | H278: Success | I278: BNKSEH56FVWJ4KK | J278: 45930
A279: PAY0007687 | B279: INV0008019 | C279: MER00381 | D279: 45961 | E279: 148.34 | F279: UPI | G279: PAYCLQF64QRKM | H279: Success | I279: BNK8LJX4L3Q65J9 | J279: 45962
A280: PAY0007688 | B280: INV0008020 | C280: MER00381 | D280: 45986 | E280: 392.57 | F280: UPI | G280: PAYQ8A9NLJRPE | H280: Success | I280: BNKEVH4E5YNRQMA | J280: 45987
A281: PAY0007689 | B281: INV0008021 | C281: MER00381 | D281: 46013 | E281: 151.19 | F281: NetBanking | G281: PAY98M6DKGUTZ | H281: Success | I281: BNKM2VTJRAU6F2B | J281: 46014
A282: PAY0007690 | B282: INV0008024 | C282: MER00381 | D282: 46105 | E282: 176.36 | F282: UPI | G282: PAYFDTY4Z3UMN | H282: Success | I282: BNK7QMVM29TK58U | J282: 46106
A283: PAY0007691 | B283: INV0008025 | C283: MER00381 | D283: 46119 | E283: 241.91 | F283: COD | G283: PAY5N9MLLV5N5 | H283: Success | I283: BNKCKLDT9LRE3BK | J283: 46120
A284: PAY0007692 | B284: INV0008028 | C284: MER00381 | D284: 46226 | E284: 85.09 | F284: UPI | G284: PAYEFZ4MTVUF5 | H284: Success | I284: BNKJW5KWBQ2DZBV | J284: 46229
A285: PAY0007693 | B285: INV0008029 | C285: MER00381 | D285: 46254 | E285: 135.29 | F285: UPI | G285: PAYNCFSUNUZXU | H285: Success | I285: BNKJZLKFE93RMWM | J285: 46257
A286: PAY0008187 | B286: INV0009635 | C286: MER00457 | D286: 45555 | E286: 766.43 | F286: Wallet | G286: PAY6BW7EDN6PP | H286: Success | I286: BNKAR4KBAWMMPL5 | J286: 45557
A287: PAY0008188 | B287: INV0009637 | C287: MER00457 | D287: 45618 | E287: 1689.49 | F287: UPI | G287: PAYAQYF5G5ZBC | H287: Success | I287: BNK8JA9MKN8V96T | J287: 45619
... A355: PAY0008648 | B355: INV0011073 | C355: MER00523 | D355: 46032 | E355: 721.27 | F355: Card | G355: PAYTQ2VLZ8KXX | H355: Success | I355: BNKYTYTNGNM4AEZ | J355: 46035
A356: PAY0008649 | B356: INV0011074 | C356: MER00523 | D356: 46048 | E356: 545.95 | F356: Wallet | G356: PAYNLMHKNNSSZ | H356: Failed | I356: BNKQHBH76Y5W68B
A357: PAY0008650 | B357: INV0011075 | C357: MER00523 | D357: 46082 | E357: 499.68 | F357: Card | G357: PAYSB64QH98A9 | H357: Success | I357: BNKWMUHS9JSHXN6 | J357: 46085
A358: PAY0008651 | B358: INV0011076 | C358: MER00523 | D358: 46108 | E358: 618.82 | F358: Card | G358: PAYWRL7QC7YDY | H358: Success | I358: BNKHBXESXNMGPNC | J358: 46111
A359: PAY0008652 | B359: INV0011077 | C359: MER00523 | D359: 46146 | E359: 528.99 | F359: UPI | G359: PAYTLX8X94GYW | H359: Success | I359: BNKVU6C9KDVNTAN | J359: 46149
A360: PAY0008653 | B360: INV0011079 | C360: MER00523 | D360: 46206 | E360: 515.47 | F360: Card | G360: PAYNYEZTBYKWE | H360: Success | I360: BNKMB9HNJSS7DUM | J360: 46208
A361: PAY0008654 | B361: INV0011080 | C361: MER00523 | D361: 46245 | E361: 557.81 | F361: UPI | G361: PAYEJ5JWFETRK | H361: Success | I361: BNKUFK84ZSPAMPC | J361: 46247
A362: PAY0008655 | B362: INV0011081 | C362: MER00523 | D362: 46267 | E362: 449.57 | F362: UPI | G362: PAYXAX5JUUGSQ | H362: Success | I362: BNK845KTMDUKP87 | J362: 46269
A363: PAY0008801 | B363: INV0011616 | C363: MER00549 | D363: 45622 | E363: 3026.5 | F363: UPI | G363: PAYUU8J2W58XM | H363: Success | I363: BNK4D3652N3DLP6 | J363: 45624
A364: PAY0008802 | B364: INV0011617 | C364: MER00549 | D364: 45650 | E364: 5883.4 | F364: UPI | G364: PAY3P3HFCWX4S | H364: Success | I364: BNKA894UZD3TDBT | J364: 45651
A365: PAY0008803 | B365: INV0011618 | C365: MER00549 | D365: 45685 | E365: 7450.02 | F365: Wallet | G365: PAY5XKAQ2M7TW | H365: Success | I365: BNK84UDZ3FWN5FP | J365: 45686
A366: PAY0008804 | B366: INV0011619 | C366: MER00549 | D366: 45711 | E366: 3424.08 | F366: Wallet | G366: PAYF2ULUU3E2E | H366: Success | I366: BNK35Z7JFTN29TB | J366: 45713
A367: PAY0008805 | B367: INV0011622 | C367: MER00549 | D367: 45794 | E367: 3434.99 | F367: NetBanking | G367: PAY9CTLUHKDYE | H367: Success | I367: BNK69VVYVZJMMBG | J367: 45795
A368: PAY0008806 | B368: INV0011623 | C368: MER00549 | D368: 45831 | E368: 4588.3 | F368: UPI | G368: PAYNSLE8LVDGT | H368: Success | I368: BNKFDGMBHMBNXE5 | J368: 45833
... A378: PAY0008816 | B378: INV0011635 | C378: MER00549 | D378: 46228 | E378: 3788.38 | F378: Card | G378: PAYET985CDACV | H378: Success | I378: BNK6REBJL3J84VT | J378: 46229
A379: PAY0008817 | B379: INV0011637 | C379: MER00549 | D379: 46286 | E379: 4345.57 | F379: UPI | G379: PAYRJFMFL34QB | H379: Failed | I379: BNK99YZSQZM8GUU
A380: PAY0009441 | B380: INV0013942 | C380: MER00658 | D380: 45549 | E380: 521.57 | F380: UPI | G380: PAY2XA4BTU35N | H380: Success | I380: BNKC4NXL9JAVL4L | J380: 45550
A381: PAY0009442 | B381: INV0013943 | C381: MER00658 | D381: 45590 | E381: 658.53 | F381: UPI | G381: PAYSEJKGXT369 | H381: Success | I381: BNKNXS8Y5LDDR6R | J381: 45593
...

Sheet Invoice Validation
A1: Invoice Validation - expected vs. billed, with XLOOKUP + IF formulas
A3: invoice_id | B3: merchant_id | C3: merchant_name | D3: expected_fee | E3: billed_fee | F3: revenue_difference | G3: variance_percent | H3: billing_status | I3: review_status
A4: INV0000956 | B4: MER00048 | C4: =XLOOKUP(B4,Merchants!$A$4:$A$1000,Merchants!$B$4:$B$1000,"Not found") | D4: =XLOOKUP(A4,tblInvoices[invoice_id],tblInvoices[expected_fee]) | E4: =XLOOKUP(A4,tblInvoices[invoice_id],tblInvoices[billed_fee]) | F4: =E4-D4 | G4: =IF(D4=0,0,ROUND(100*F4/D4,2)) | H4: =IF(ABS(F4)<=0.01,"Correct",IF(F4<0,"Underbilled","Overbilled"))
A5: INV0000957 | B5: MER00048 | C5: =XLOOKUP(B5,Merchants!$A$4:$A$1000,Merchants!$B$4:$B$1000,"Not found") | D5: =XLOOKUP(A5,tblInvoices[invoice_id],tblInvoices[expected_fee]) | E5: =XLOOKUP(A5,tblInvoices[invoice_id],tblInvoices[billed_fee]) | F5: =E5-D5 | G5: =IF(D5=0,0,ROUND(100*F5/D5,2)) | H5: =IF(ABS(F5)<=0.01,"Correct",IF(F5<0,"Underbilled","Overbilled"))
A6: INV0000958 | B6: MER00048 | C6: =XLOOKUP(B6,Merchants!$A$4:$A$1000,Merchants!$B$4:$B$1000,"Not found") | D6: =XLOOKUP(A6,tblInvoices[invoice_id],tblInvoices[expected_fee]) | E6: =XLOOKUP(A6,tblInvoices[invoice_id],tblInvoices[billed_fee]) | F6: =E6-D6 | G6: =IF(D6=0,0,ROUND(100*F6/D6,2)) | H6: =IF(ABS(F6)<=0.01,"Correct",IF(F6<0,"Underbilled","Overbilled"))
A7: INV0000959 | B7: MER00048 | C7: =XLOOKUP(B7,Merchants!$A$4:$A$1000,Merchants!$B$4:$B$1000,"Not found") | D7: =XLOOKUP(A7,tblInvoices[invoice_id],tblInvoices[expected_fee]) | E7: =XLOOKUP(A7,tblInvoices[invoice_id],tblInvoices[billed_fee]) | F7: =E7-D7 | G7: =IF(D7=0,0,ROUND(100*F7/D7,2)) | H7: =IF(ABS(F7)<=0.01,"Correct",IF(F7<0,"Underbilled","Overbilled"))
A8: INV0000960 | B8: MER00048 | C8: =XLOOKUP(B8,Merchants!$A$4:$A$1000,Merchants!$B$4:$B$1000,"Not found") | D8: =XLOOKUP(A8,tblInvoices[invoice_id],tblInvoices[expected_fee]) | E8: =XLOOKUP(A8,tblInvoices[invoice_id],tblInvoices[billed_fee]) | F8: =E8-D8 | G8: =IF(D8=0,0,ROUND(100*F8/D8,2)) | H8: =IF(ABS(F8)<=0.01,"Correct",IF(F8<0,"Underbilled","Overbilled"))
A9: INV0000961 | B9: MER00048 | C9: =XLOOKUP(B9,Merchants!$A$4:$A$1000,Merchants!$B$4:$B$1000,"Not found") | D9: =XLOOKUP(A9,tblInvoices[invoice_id],tblInvoices[expected_fee]) | E9: =XLOOKUP(A9,tblInvoices[invoice_id],tblInvoices[billed_fee]) | F9: =E9-D9 | G9: =IF(D9=0,0,ROUND(100*F9/D9,2)) | H9: =IF(ABS(F9)<=0.01,"Correct",IF(F9<0,"Underbilled","Overbilled"))
A10: INV0000962 | B10: MER00048 | C10: =XLOOKUP(B10,Merchants!$A$4:$A$1000,Merchants!$B$4:$B$1000,"Not found") | D10: =XLOOKUP(A10,tblInvoices[invoice_id],tblInvoices[expected_fee]) | E10: =XLOOKUP(A10,tblInvoices[invoice_id],tblInvoices[billed_fee]) | F10: =E10-D10 | G10: =IF(D10=0,0,ROUND(100*F10/D10,2)) | H10: =IF(ABS(F10)<=0.01,"Correct",IF(F10<0,"Underbilled","Overbilled"))
A11: INV0000963 | B11: MER00048 | C11: =XLOOKUP(B11,Merchants!$A$4:$A$1000,Merchants!$B$4:$B$1000,"Not found") | D11: =XLOOKUP(A11,tblInvoices[invoice_id],tblInvoices[expected_fee]) | E11: =XLOOKUP(A11,tblInvoices[invoice_id],tblInvoices[billed_fee]) | F11: =E11-D11 | G11: =IF(D11=0,0,ROUND(100*F11/D11,2)) | H11: =IF(ABS(F11)<=0.01,"Correct",IF(F11<0,"Underbilled","Overbilled"))
A12: INV0000964 | B12: MER00048 | C12: =XLOOKUP(B12,Merchants!$A$4:$A$1000,Merchants!$B$4:$B$1000,"Not found") | D12: =XLOOKUP(A12,tblInvoices[invoice_id],tblInvoices[expected_fee]) | E12: =XLOOKUP(A12,tblInvoices[invoice_id],tblInvoices[billed_fee]) | F12: =E12-D12 | G12: =IF(D12=0,0,ROUND(100*F12/D12,2)) | H12: =IF(ABS(F12)<=0.01,"Correct",IF(F12<0,"Underbilled","Overbilled"))
A13: INV0000965 | B13: MER00048 | C13: =XLOOKUP(B13,Merchants!$A$4:$A$1000,Merchants!$B$4:$B$1000,"Not found") | D13: =XLOOKUP(A13,tblInvoices[invoice_id],tblInvoices[expected_fee]) | E13: =XLOOKUP(A13,tblInvoices[invoice_id],tblInvoices[billed_fee]) | F13: =E13-D13 | G13: =IF(D13=0,0,ROUND(100*F13/D13,2)) | H13: =IF(ABS(F13)<=0.01,"Correct",IF(F13<0,"Underbilled","Overbilled"))
A14: INV0000966 | B14: MER00048 | C14: =XLOOKUP(B14,Merchants!$A$4:$A$1000,Merchants!$B$4:$B$1000,"Not found") | D14: =XLOOKUP(A14,tblInvoices[invoice_id],tblInvoices[expected_fee]) | E14: =XLOOKUP(A14,tblInvoices[invoice_id],tblInvoices[billed_fee]) | F14: =E14-D14 | G14: =IF(D14=0,0,ROUND(100*F14/D14,2)) | H14: =IF(ABS(F14)<=0.01,"Correct",IF(F14<0,"Underbilled","Overbilled"))
A15: INV0000967 | B15: MER00048 | C15: =XLOOKUP(B15,Merchants!$A$4:$A$1000,Merchants!$B$4:$B$1000,"Not found") | D15: =XLOOKUP(A15,tblInvoices[invoice_id],tblInvoices[expected_fee]) | E15: =XLOOKUP(A15,tblInvoices[invoice_id],tblInvoices[billed_fee]) | F15: =E15-D15 | G15: =IF(D15=0,0,ROUND(100*F15/D15,2)) | H15: =IF(ABS(F15)<=0.01,"Correct",IF(F15<0,"Underbilled","Overbilled"))
... A898: INV0019140 | B898: MER00902 | C898: =XLOOKUP(B898,Merchants!$A$4:$A$1000,Merchants!$B$4:$B$1000,"Not found") | D898: =XLOOKUP(A898,tblInvoices[invoice_id],tblInvoices[expected_fee]) | E898: =XLOOKUP(A898,tblInvoices[invoice_id],tblInvoices[billed_fee]) | F898: =E898-D898 | G898: =IF(D898=0,0,ROUND(100*F898/D898,2)) | H898: =IF(ABS(F898)<=0.01,"Correct",IF(F898<0,"Underbilled","Overbilled"))

Sheet AR Aging
A1: AR Aging - SUMIFS against Payments, aging bucket via IFS
A2: As-of date: 2026-08-13
A4: invoice_id | B4: merchant_id | C4: merchant_name | D4: due_date | E4: total_invoice_amount | F4: total_paid | G4: outstanding_amount | H4: days_overdue | I4: aging_bucket
A5: INV0000956 | B5: MER00048 | C5: =XLOOKUP(B5,Merchants!$A$4:$A$1000,Merchants!$B$4:$B$1000,"Not found") | D5: =XLOOKUP(A5,tblInvoices[invoice_id],tblInvoices[due_date]) | E5: =XLOOKUP(A5,tblInvoices[invoice_id],tblInvoices[total_invoice_amount]) | F5: =SUMIFS(tblPayments[payment_amount],tblPayments[invoice_id],A5,tblPayments[payment_status],"Success") | G5: =MAX(0,E5-F5) | H5: =DATE(2026,8,13)-D5 | I5: =IFS(G5=0,"Excluded (paid)",H5<=0,"Current",H5<=30,"1-30 days",H5<=60,"31-60 days",H5<=90,"61-90 days",TRUE,"90+ days")
A6: INV0000957 | B6: MER00048 | C6: =XLOOKUP(B6,Merchants!$A$4:$A$1000,Merchants!$B$4:$B$1000,"Not found") | D6: =XLOOKUP(A6,tblInvoices[invoice_id],tblInvoices[due_date]) | E6: =XLOOKUP(A6,tblInvoices[invoice_id],tblInvoices[total_invoice_amount]) | F6: =SUMIFS(tblPayments[payment_amount],tblPayments[invoice_id],A6,tblPayments[payment_status],"Success") | G6: =MAX(0,E6-F6) | H6: =DATE(2026,8,13)-D6 | I6: =IFS(G6=0,"Excluded (paid)",H6<=0,"Current",H6<=30,"1-30 days",H6<=60,"31-60 days",H6<=90,"61-90 days",TRUE,"90+ days")
A7: INV0000958 | B7: MER00048 | C7: =XLOOKUP(B7,Merchants!$A$4:$A$1000,Merchants!$B$4:$B$1000,"Not found") | D7: =XLOOKUP(A7,tblInvoices[invoice_id],tblInvoices[due_date]) | E7: =XLOOKUP(A7,tblInvoices[invoice_id],tblInvoices[total_invoice_amount]) | F7: =SUMIFS(tblPayments[payment_amount],tblPayments[invoice_id],A7,tblPayments[payment_status],"Success") | G7: =MAX(0,E7-F7) | H7: =DATE(2026,8,13)-D7 | I7: =IFS(G7=0,"Excluded (paid)",H7<=0,"Current",H7<=30,"1-30 days",H7<=60,"31-60 days",H7<=90,"61-90 days",TRUE,"90+ days")
A8: INV0000959 | B8: MER00048 | C8: =XLOOKUP(B8,Merchants!$A$4:$A$1000,Merchants!$B$4:$B$1000,"Not found") | D8: =XLOOKUP(A8,tblInvoices[invoice_id],tblInvoices[due_date]) | E8: =XLOOKUP(A8,tblInvoices[invoice_id],tblInvoices[total_invoice_amount]) | F8: =SUMIFS(tblPayments[payment_amount],tblPayments[invoice_id],A8,tblPayments[payment_status],"Success") | G8: =MAX(0,E8-F8) | H8: =DATE(2026,8,13)-D8 | I8: =IFS(G8=0,"Excluded (paid)",H8<=0,"Current",H8<=30,"1-30 days",H8<=60,"31-60 days",H8<=90,"61-90 days",TRUE,"90+ days")
A9: INV0000960 | B9: MER00048 | C9: =XLOOKUP(B9,Merchants!$A$4:$A$1000,Merchants!$B$4:$B$1000,"Not found") | D9: =XLOOKUP(A9,tblInvoices[invoice_id],tblInvoices[due_date]) | E9: =XLOOKUP(A9,tblInvoices[invoice_id],tblInvoices[total_invoice_amount]) | F9: =SUMIFS(tblPayments[payment_amount],tblPayments[invoice_id],A9,tblPayments[payment_status],"Success") | G9: =MAX(0,E9-F9) | H9: =DATE(2026,8,13)-D9 | I9: =IFS(G9=0,"Excluded (paid)",H9<=0,"Current",H9<=30,"1-30 days",H9<=60,"31-60 days",H9<=90,"61-90 days",TRUE,"90+ days")
A10: INV0000961 | B10: MER00048 | C10: =XLOOKUP(B10,Merchants!$A$4:$A$1000,Merchants!$B$4:$B$1000,"Not found") | D10: =XLOOKUP(A10,tblInvoices[invoice_id],tblInvoices[due_date]) | E10: =XLOOKUP(A10,tblInvoices[invoice_id],tblInvoices[total_invoice_amount]) | F10: =SUMIFS(tblPayments[payment_amount],tblPayments[invoice_id],A10,tblPayments[payment_status],"Success") | G10: =MAX(0,E10-F10) | H10: =DATE(2026,8,13)-D10 | I10: =IFS(G10=0,"Excluded (paid)",H10<=0,"Current",H10<=30,"1-30 days",H10<=60,"31-60 days",H10<=90,"61-90 days",TRUE,"90+ days")
A11: INV0000962 | B11: MER00048 | C11: =XLOOKUP(B11,Merchants!$A$4:$A$1000,Merchants!$B$4:$B$1000,"Not found") | D11: =XLOOKUP(A11,tblInvoices[invoice_id],tblInvoices[due_date]) | E11: =XLOOKUP(A11,tblInvoices[invoice_id],tblInvoices[total_invoice_amount]) | F11: =SUMIFS(tblPayments[payment_amount],tblPayments[invoice_id],A11,tblPayments[payment_status],"Success") | G11: =MAX(0,E11-F11) | H11: =DATE(2026,8,13)-D11 | I11: =IFS(G11=0,"Excluded (paid)",H11<=0,"Current",H11<=30,"1-30 days",H11<=60,"31-60 days",H11<=90,"61-90 days",TRUE,"90+ days")
A12: INV0000963 | B12: MER00048 | C12: =XLOOKUP(B12,Merchants!$A$4:$A$1000,Merchants!$B$4:$B$1000,"Not found") | D12: =XLOOKUP(A12,tblInvoices[invoice_id],tblInvoices[due_date]) | E12: =XLOOKUP(A12,tblInvoices[invoice_id],tblInvoices[total_invoice_amount]) | F12: =SUMIFS(tblPayments[payment_amount],tblPayments[invoice_id],A12,tblPayments[payment_status],"Success") | G12: =MAX(0,E12-F12) | H12: =DATE(2026,8,13)-D12 | I12: =IFS(G12=0,"Excluded (paid)",H12<=0,"Current",H12<=30,"1-30 days",H12<=60,"31-60 days",H12<=90,"61-90 days",TRUE,"90+ days")
A13: INV0000964 | B13: MER00048 | C13: =XLOOKUP(B13,Merchants!$A$4:$A$1000,Merchants!$B$4:$B$1000,"Not found") | D13: =XLOOKUP(A13,tblInvoices[invoice_id],tblInvoices[due_date]) | E13: =XLOOKUP(A13,tblInvoices[invoice_id],tblInvoices[total_invoice_amount]) | F13: =SUMIFS(tblPayments[payment_amount],tblPayments[invoice_id],A13,tblPayments[payment_status],"Success") | G13: =MAX(0,E13-F13) | H13: =DATE(2026,8,13)-D13 | I13: =IFS(G13=0,"Excluded (paid)",H13<=0,"Current",H13<=30,"1-30 days",H13<=60,"31-60 days",H13<=90,"61-90 days",TRUE,"90+ days")
A14: INV0000965 | B14: MER00048 | C14: =XLOOKUP(B14,Merchants!$A$4:$A$1000,Merchants!$B$4:$B$1000,"Not found") | D14: =XLOOKUP(A14,tblInvoices[invoice_id],tblInvoices[due_date]) | E14: =XLOOKUP(A14,tblInvoices[invoice_id],tblInvoices[total_invoice_amount]) | F14: =SUMIFS(tblPayments[payment_amount],tblPayments[invoice_id],A14,tblPayments[payment_status],"Success") | G14: =MAX(0,E14-F14) | H14: =DATE(2026,8,13)-D14 | I14: =IFS(G14=0,"Excluded (paid)",H14<=0,"Current",H14<=30,"1-30 days",H14<=60,"31-60 days",H14<=90,"61-90 days",TRUE,"90+ days")
A15: INV0000966 | B15: MER00048 | C15: =XLOOKUP(B15,Merchants!$A$4:$A$1000,Merchants!$B$4:$B$1000,"Not found") | D15: =XLOOKUP(A15,tblInvoices[invoice_id],tblInvoices[due_date]) | E15: =XLOOKUP(A15,tblInvoices[invoice_id],tblInvoices[total_invoice_amount]) | F15: =SUMIFS(tblPayments[payment_amount],tblPayments[invoice_id],A15,tblPayments[payment_status],"Success") | G15: =MAX(0,E15-F15) | H15: =DATE(2026,8,13)-D15 | I15: =IFS(G15=0,"Excluded (paid)",H15<=0,"Current",H15<=30,"1-30 days",H15<=60,"31-60 days",H15<=90,"61-90 days",TRUE,"90+ days")
A16: INV0000967 | B16: MER00048 | C16: =XLOOKUP(B16,Merchants!$A$4:$A$1000,Merchants!$B$4:$B$1000,"Not found") | D16: =XLOOKUP(A16,tblInvoices[invoice_id],tblInvoices[due_date]) | E16: =XLOOKUP(A16,tblInvoices[invoice_id],tblInvoices[total_invoice_amount]) | F16: =SUMIFS(tblPayments[payment_amount],tblPayments[invoice_id],A16,tblPayments[payment_status],"Success") | G16: =MAX(0,E16-F16) | H16: =DATE(2026,8,13)-D16 | I16: =IFS(G16=0,"Excluded (paid)",H16<=0,"Current",H16<=30,"1-30 days",H16<=60,"31-60 days",H16<=90,"61-90 days",TRUE,"90+ days")
... A899: INV0019140 | B899: MER00902 | C899: =XLOOKUP(B899,Merchants!$A$4:$A$1000,Merchants!$B$4:$B$1000,"Not found") | D899: =XLOOKUP(A899,tblInvoices[invoice_id],tblInvoices[due_date]) | E899: =XLOOKUP(A899,tblInvoices[invoice_id],tblInvoices[total_invoice_amount]) | F899: =SUMIFS(tblPayments[payment_amount],tblPayments[invoice_id],A899,tblPayments[payment_status],"Success") | G899: =MAX(0,E899-F899) | H899: =DATE(2026,8,13)-D899 | I899: =IFS(G899=0,"Excluded (paid)",H899<=0,"Current",H899<=30,"1-30 days",H899<=60,"31-60 days",H899<=90,"61-90 days",TRUE,"90+ days")
A902: Aging Summary
A903: Bucket | B903: Invoice Count | C903: Total Outstanding
A904: Current | B904: =COUNTIFS(I5:I899,A904) | C904: =SUMIFS(G5:G899,I5:I899,A904)
A905: 1-30 days | B905: =COUNTIFS(I5:I899,A905) | C905: =SUMIFS(G5:G899,I5:I899,A905)
A906: 31-60 days | B906: =COUNTIFS(I5:I899,A906) | C906: =SUMIFS(G5:G899,I5:I899,A906)
A907: 61-90 days | B907: =COUNTIFS(I5:I899,A907) | C907: =SUMIFS(G5:G899,I5:I899,A907)
A908: 90+ days | B908: =COUNTIFS(I5:I899,A908) | C908: =SUMIFS(G5:G899,I5:I899,A908)

Sheet Collections
A1: Collection Activity - with outcome-effectiveness SUMIFS/COUNTIFS summary
A3: collection_id | B3: merchant_id | C3: invoice_id | D3: activity_date | E3: activity_type | F3: contact_channel | G3: collector | H3: outcome | I3: promised_payment_date | J3: promised_amount | K3: notes
A4: COL0000558 | B4: MER00055 | C4: INV0001101 | D4: 45570 | E4: Reminder | F4: Email | G4: Nandini Rajan | H4: No Response | K4: Automated reminder sent for invoice INV0001101 due 2024-10-02.
A5: COL0000559 | B5: MER00055 | C5: INV0001101 | D5: 45583 | E5: Email | F5: Email | G5: Vivek Nair | H5: No Response | K5: Followed up via email regarding outstanding invoice INV0001101.
A6: COL0000560 | B6: MER00055 | C6: INV0001101 | D6: 45589 | E6: Phone | F6: Phone | G6: Amit Saxena | H6: No Response | K6: Called merchant to discuss overdue invoice INV0001101.
A7: COL0000561 | B7: MER00055 | C7: INV0001101 | D7: 45599 | E7: Escalation | F7: Phone | G7: Ritu Bansal | H7: Escalated | K7: Escalated invoice INV0001101 to account manager for non-payment.
A8: COL0000562 | B8: MER00055 | C8: INV0001102 | D8: 45603 | E8: Reminder | F8: Email | G8: Farhan Sheikh | H8: No Response | K8: Automated reminder sent for invoice INV0001102 due 2024-11-01.
A9: COL0000563 | B9: MER00055 | C9: INV0001102 | D9: 45616 | E9: Email | F9: Email | G9: Shweta Gupta | H9: No Response | K9: Followed up via email regarding outstanding invoice INV0001102.
A10: COL0000564 | B10: MER00055 | C10: INV0001102 | D10: 45628 | E10: Phone | F10: Phone | G10: Shweta Gupta | H10: No Response | K10: Called merchant to discuss overdue invoice INV0001102.
A11: COL0000565 | B11: MER00055 | C11: INV0001102 | D11: 45634 | E11: Escalation | F11: Phone | G11: Ritu Bansal | H11: Escalated | K11: Escalated invoice INV0001102 to account manager for non-payment.
A12: COL0000566 | B12: MER00055 | C12: INV0001102 | D12: 45642 | E12: Payment Promise | F12: WhatsApp | G12: Ritu Bansal | H12: No Response | I12: 45651 | J12: 614.61 | K12: Merchant committed to paying invoice INV0001102 by 2024-12-25.
A13: COL0000567 | B13: MER00055 | C13: INV0001103 | D13: 45637 | E13: Reminder | F13: Email | G13: Farhan Sheikh | H13: No Response | K13: Automated reminder sent for invoice INV0001103 due 2024-12-02.
A14: COL0000568 | B14: MER00055 | C14: INV0001103 | D14: 45649 | E14: Email | F14: Email | G14: Amit Saxena | H14: Promise to Pay | I14: 45657 | J14: 718.84 | K14: Followed up via email regarding outstanding invoice INV0001103.
A15: COL0000569 | B15: MER00055 | C15: INV0001103 | D15: 45663 | E15: Phone | F15: Phone | G15: Amit Saxena | H15: Promise to Pay | I15: 45668 | J15: 1216.84 | K15: Called merchant to discuss overdue invoice INV0001103.
A16: COL0000570 | B16: MER00055 | C16: INV0001103 | D16: 45677 | E16: Escalation | F16: Phone | G16: Amit Saxena | H16: No Response | K16: Escalated invoice INV0001103 to account manager for non-payment.
A17: COL0000571 | B17: MER00055 | C17: INV0001103 | D17: 45682 | E17: Payment Promise | F17: WhatsApp | G17: Shweta Gupta | H17: Promise to Pay | I17: 45688 | J17: 888.13 | K17: Merchant committed to paying invoice INV0001103 by 2025-01-31.
A18: COL0000572 | B18: MER00055 | C18: INV0001109 | D18: 45846 | E18: Reminder | F18: Email | G18: Sanjay Kumar | H18: No Response | K18: Automated reminder sent for invoice INV0001109 due 2025-07-02.
A19: COL0000573 | B19: MER00055 | C19: INV0001109 | D19: 45853 | E19: Email | F19: Email | G19: Manish Tiwari | H19: No Response | K19: Followed up via email regarding outstanding invoice INV0001109.
A20: COL0000574 | B20: MER00055 | C20: INV0001109 | D20: 45866 | E20: Phone | F20: Phone | G20: Anjali Desai | H20: No Response | K20: Called merchant to discuss overdue invoice INV0001109.
A21: COL0000575 | B21: MER00055 | C21: INV0001109 | D21: 45871 | E21: Escalation | F21: Phone | G21: Farhan Sheikh | H21: No Response | K21: Escalated invoice INV0001109 to account manager for non-payment.
A22: COL0000576 | B22: MER00055 | C22: INV0001110 | D22: 45875 | E22: Reminder | F22: Email | G22: Vivek Nair | H22: No Response | K22: Automated reminder sent for invoice INV0001110 due 2025-08-01.
A23: COL0000577 | B23: MER00055 | C23: INV0001110 | D23: 45880 | E23: Email | F23: Email | G23: Shweta Gupta | H23: Promise to Pay | I23: 45894 | J23: 475.4 | K23: Followed up via email regarding outstanding invoice INV0001110.
A24: COL0000578 | B24: MER00055 | C24: INV0001110 | D24: 45891 | E24: Phone | F24: Phone | G24: Farhan Sheikh | H24: Disputed | K24: Called merchant to discuss overdue invoice INV0001110.
A25: COL0000579 | B25: MER00055 | C25: INV0001110 | D25: 45902 | E25: Escalation | F25: Phone | G25: Shweta Gupta | H25: Payment Received | K25: Escalated invoice INV0001110 to account manager for non-payment.
A26: COL0000580 | B26: MER00055 | C26: INV0001112 | D26: 45938 | E26: Reminder | F26: Email | G26: Manish Tiwari | H26: No Response | K26: Automated reminder sent for invoice INV0001112 due 2025-10-02.
A27: COL0000581 | B27: MER00055 | C27: INV0001112 | D27: 45948 | E27: Email | F27: Email | G27: Vivek Nair | H27: Promise to Pay | I27: 45959 | J27: 666.58 | K27: Followed up via email regarding outstanding invoice INV0001112.
A28: COL0000582 | B28: MER00055 | C28: INV0001112 | D28: 45956 | E28: Phone | F28: Phone | G28: Nandini Rajan | H28: No Response | K28: Called merchant to discuss overdue invoice INV0001112.
A29: COL0000583 | B29: MER00055 | C29: INV0001112 | D29: 45966 | E29: Escalation | F29: Phone | G29: Ritu Bansal | H29: Disputed | K29: Escalated invoice INV0001112 to account manager for non-payment.
A30: COL0000584 | B30: MER00055 | C30: INV0001112 | D30: 45978 | E30: Payment Promise | F30: WhatsApp | G30: Vivek Nair | H30: No Response | I30: 45984 | J30: 910.27 | K30: Merchant committed to paying invoice INV0001112 by 2025-11-23.
A31: COL0000585 | B31: MER00055 | C31: INV0001114 | D31: 46002 | E31: Reminder | F31: Email | G31: Farhan Sheikh | H31: Promise to Pay | I31: 46014 | J31: 851.88 | K31: Automated reminder sent for invoice INV0001114 due 2025-12-02.
A32: COL0000586 | B32: MER00055 | C32: INV0001114 | D32: 46013 | E32: Email | F32: Email | G32: Anjali Desai | H32: No Response | K32: Followed up via email regarding outstanding invoice INV0001114.
A33: COL0000587 | B33: MER00055 | C33: INV0001114 | D33: 46023 | E33: Phone | F33: Phone | G33: Anjali Desai | H33: No Response | K33: Called merchant to discuss overdue invoice INV0001114.
A34: COL0000588 | B34: MER00055 | C34: INV0001120 | D34: 46181 | E34: Reminder | F34: Email | G34: Manish Tiwari | H34: Promise to Pay | I34: 46185 | J34: 1301.11 | K34: Automated reminder sent for invoice INV0001120 due 2026-06-01.
A35: COL0000589 | B35: MER00055 | C35: INV0001120 | D35: 46189 | E35: Email | F35: Email | G35: Manish Tiwari | H35: Promise to Pay | I35: 46201 | J35: 1222.28 | K35: Followed up via email regarding outstanding invoice INV0001120.
A36: COL0000590 | B36: MER00055 | C36: INV0001120 | D36: 46196 | E36: Phone | F36: Phone | G36: Shweta Gupta | H36: No Response | K36: Called merchant to discuss overdue invoice INV0001120.
A37: COL0000591 | B37: MER00055 | C37: INV0001120 | D37: 46205 | E37: Escalation | F37: Phone | G37: Shweta Gupta | H37: Disputed | K37: Escalated invoice INV0001120 to account manager for non-payment.
A38: COL0000592 | B38: MER00055 | C38: INV0001122 | D38: 46241 | E38: Reminder | F38: Email | G38: Shweta Gupta | H38: Promise to Pay | I38: 46244 | J38: 1609.59 | K38: Automated reminder sent for invoice INV0001122 due 2026-08-01.
A39: COL0000593 | B39: MER00055 | C39: INV0001122 | D39: 46249 | E39: Email | F39: Email | G39: Nandini Rajan | H39: No Response | K39: Followed up via email regarding outstanding invoice INV0001122.
A40: COL0000594 | B40: MER00055 | C40: INV0001122 | D40: 46257 | E40: Phone | F40: Phone | G40: Sanjay Kumar | H40: No Response | K40: Called merchant to discuss overdue invoice INV0001122.
A41: COL0000595 | B41: MER00055 | C41: INV0001122 | D41: 46264 | E41: Escalation | F41: Phone | G41: Anjali Desai | H41: Disputed | K41: Escalated invoice INV0001122 to account manager for non-payment.
A42: COL0000596 | B42: MER00055 | C42: INV0001122 | D42: 46274 | E42: Payment Promise | F42: WhatsApp | G42: Farhan Sheikh | H42: No Response | I42: 46288 | J42: 921.18 | K42: Merchant committed to paying invoice INV0001122 by 2026-09-23.
A43: COL0000774 | B43: MER00074 | C43: INV0001548 | D43: 45858 | E43: Reminder | F43: Email | G43: Anjali Desai | H43: No Response | K43: Automated reminder sent for invoice INV0001548 due 2025-07-17.
A44: COL0000775 | B44: MER00074 | C44: INV0001548 | D44: 45872 | E44: Email | F44: Email | G44: Anjali Desai | H44: Promise to Pay | I44: 45883 | J44: 1244.7 | K44: Followed up via email regarding outstanding invoice INV0001548.
A45: COL0000776 | B45: MER00074 | C45: INV0001550 | D45: 45925 | E45: Reminder | F45: Email | G45: Sanjay Kumar | H45: No Response | K45: Automated reminder sent for invoice INV0001550 due 2025-09-16.
A46: COL0000777 | B46: MER00074 | C46: INV0001550 | D46: 45937 | E46: Email | F46: Email | G46: Nandini Rajan | H46: No Response | K46: Followed up via email regarding outstanding invoice INV0001550.
A47: COL0000778 | B47: MER00074 | C47: INV0001550 | D47: 45951 | E47: Phone | F47: Phone | G47: Ritu Bansal | H47: Promise to Pay | I47: 45962 | J47: 852.79 | K47: Called merchant to discuss overdue invoice INV0001550.
A48: COL0000779 | B48: MER00074 | C48: INV0001557 | D48: 46136 | E48: Reminder | F48: Email | G48: Manish Tiwari | H48: Promise to Pay | I48: 46147 | J48: 1654.33 | K48: Automated reminder sent for invoice INV0001557 due 2026-04-16.
A49: COL0000791 | B49: MER00077 | C49: INV0001630 | D49: 46163 | E49: Reminder | F49: Email | G49: Nandini Rajan | H49: Promise to Pay | I49: 46166 | J49: 351.39 | K49: Automated reminder sent for invoice INV0001630 due 2026-05-17.
A50: COL0001466 | B50: MER00139 | C50: INV0002949 | D50: 45692 | E50: Reminder | F50: Email | G50: Farhan Sheikh | H50: No Response | K50: Automated reminder sent for invoice INV0002949 due 2025-01-31.
A51: COL0001467 | B51: MER00139 | C51: INV0002949 | D51: 45698 | E51: Email | F51: Email | G51: Farhan Sheikh | H51: No Response | K51: Followed up via email regarding outstanding invoice INV0002949.
A52: COL0001468 | B52: MER00139 | C52: INV0002949 | D52: 45709 | E52: Phone | F52: Phone | G52: Amit Saxena | H52: No Response | K52: Called merchant to discuss overdue invoice INV0002949.
A53: COL0001469 | B53: MER00139 | C53: INV0002957 | D53: 45971 | E53: Reminder | F53: Email | G53: Ritu Bansal | H53: No Response | K53: Automated reminder sent for invoice INV0002957 due 2025-11-01.
A54: COL0001470 | B54: MER00139 | C54: INV0002957 | D54: 45985 | E54: Email | F54: Email | G54: Vivek Nair | H54: No Response | K54: Followed up via email regarding outstanding invoice INV0002957.
A55: COL0001471 | B55: MER00139 | C55: INV0002957 | D55: 45991 | E55: Phone | F55: Phone | G55: Amit Saxena | H55: Promise to Pay | I55: 46000 | J55: 1381.46 | K55: Called merchant to discuss overdue invoice INV0002957.
A56: COL0001472 | B56: MER00139 | C56: INV0002958 | D56: 45998 | E56: Reminder | F56: Email | G56: Manish Tiwari | H56: No Response | K56: Automated reminder sent for invoice INV0002958 due 2025-12-01.
A57: COL0001473 | B57: MER00139 | C57: INV0002958 | D57: 46011 | E57: Email | F57: Email | G57: Anjali Desai | H57: No Response | K57: Followed up via email regarding outstanding invoice INV0002958.
A58: COL0001474 | B58: MER00139 | C58: INV0002958 | D58: 46021 | E58: Phone | F58: Phone | G58: Farhan Sheikh | H58: Promise to Pay | I58: 46030 | J58: 758.1 | K58: Called merchant to discuss overdue invoice INV0002958.
A59: COL0001475 | B59: MER00139 | C59: INV0002958 | D59: 46030 | E59: Escalation | F59: Phone | G59: Ritu Bansal | H59: Escalated | K59: Escalated invoice INV0002958 to account manager for non-payment.
A60: COL0001476 | B60: MER00139 | C60: INV0002959 | D60: 46032 | E60: Reminder | F60: Email | G60: Manish Tiwari | H60: No Response | K60: Automated reminder sent for invoice INV0002959 due 2026-01-01.
A61: COL0001477 | B61: MER00139 | C61: INV0002959 | D61: 46038 | E61: Email | F61: Email | G61: Manish Tiwari | H61: Promise to Pay | I61: 46047 | J61: 1358.56 | K61: Followed up via email regarding outstanding invoice INV0002959.
A62: COL0001478 | B62: MER00139 | C62: INV0002959 | D62: 46045 | E62: Phone | F62: Phone | G62: Sanjay Kumar | H62: Promise to Pay | I62: 46055 | J62: 1539.21 | K62: Called merchant to discuss overdue invoice INV0002959.
A63: COL0001479 | B63: MER00140 | C63: INV0002975 | D63: 45736 | E63: Reminder | F63: Email | G63: Anjali Desai | H63: No Response | K63: Automated reminder sent for invoice INV0002975 due 2025-03-17.
A64: COL0001480 | B64: MER00140 | C64: INV0002975 | D64: 45744 | E64: Email | F64: Email | G64: Sanjay Kumar | H64: No Response | K64: Followed up via email regarding outstanding invoice INV0002975.
A65: COL0001481 | B65: MER00140 | C65: INV0002975 | D65: 45749 | E65: Phone | F65: Phone | G65: Sanjay Kumar | H65: No Response | K65: Called merchant to discuss overdue invoice INV0002975.
A66: COL0001482 | B66: MER00140 | C66: INV0002976 | D66: 45768 | E66: Reminder | F66: Email | G66: Farhan Sheikh | H66: Promise to Pay | I66: 45782 | J66: 207.42 | K66: Automated reminder sent for invoice INV0002976 due 2025-04-17.
A67: COL0001483 | B67: MER00140 | C67: INV0002976 | D67: 45774 | E67: Email | F67: Email | G67: Farhan Sheikh | H67: No Response | K67: Followed up via email regarding outstanding invoice INV0002976.
A68: COL0001484 | B68: MER00140 | C68: INV0002976 | D68: 45784 | E68: Phone | F68: Phone | G68: Nandini Rajan | H68: No Response | K68: Called merchant to discuss overdue invoice INV0002976.
A69: COL0001485 | B69: MER00140 | C69: INV0002976 | D69: 45798 | E69: Escalation | F69: Phone | G69: Ritu Bansal | H69: Escalated | K69: Escalated invoice INV0002976 to account manager for non-payment.
A70: COL0001486 | B70: MER00140 | C70: INV0002976 | D70: 45807 | E70: Payment Promise | F70: WhatsApp | G70: Manish Tiwari | H70: Payment Received | I70: 45819 | J70: 211.28 | K70: Merchant committed to paying invoice INV0002976 by 2025-06-11.
A71: COL0001487 | B71: MER00140 | C71: INV0002977 | D71: 45803 | E71: Reminder | F71: Email | G71: Nandini Rajan | H71: No Response | K71: Automated reminder sent for invoice INV0002977 due 2025-05-17.
A72: COL0001488 | B72: MER00140 | C72: INV0002977 | D72: 45811 | E72: Email | F72: Email | G72: Ritu Bansal | H72: No Response | K72: Followed up via email regarding outstanding invoice INV0002977.
A73: COL0001489 | B73: MER00140 | C73: INV0002977 | D73: 45824 | E73: Phone | F73: Phone | G73: Anjali Desai | H73: No Response | K73: Called merchant to discuss overdue invoice INV0002977.
A74: COL0001490 | B74: MER00140 | C74: INV0002979 | D74: 45861 | E74: Reminder | F74: Email | G74: Anjali Desai | H74: No Response | K74: Automated reminder sent for invoice INV0002979 due 2025-07-17.
A75: COL0001491 | B75: MER00140 | C75: INV0002979 | D75: 45875 | E75: Email | F75: Email | G75: Amit Saxena | H75: Promise to Pay | I75: 45880 | J75: 172.05 | K75: Followed up via email regarding outstanding invoice INV0002979.
A76: COL0001492 | B76: MER00140 | C76: INV0002979 | D76: 45882 | E76: Phone | F76: Phone | G76: Anjali Desai | H76: Disputed | K76: Called merchant to discuss overdue invoice INV0002979.
A77: COL0001493 | B77: MER00140 | C77: INV0002979 | D77: 45892 | E77: Escalation | F77: Phone | G77: Anjali Desai | H77: Escalated | K77: Escalated invoice INV0002979 to account manager for non-payment.
A78: COL0001494 | B78: MER00140 | C78: INV0002979 | D78: 45902 | E78: Payment Promise | F78: WhatsApp | G78: Farhan Sheikh | H78: No Response | I78: 45915 | J78: 196.65 | K78: Merchant committed to paying invoice INV0002979 by 2025-09-15.
A79: COL0001495 | B79: MER00140 | C79: INV0002982 | D79: 45954 | E79: Reminder | F79: Email | G79: Anjali Desai | H79: No Response | K79: Automated reminder sent for invoice INV0002982 due 2025-10-17.
A80: COL0001496 | B80: MER00140 | C80: INV0002982 | D80: 45963 | E80: Email | F80: Email | G80: Shweta Gupta | H80: Promise to Pay | I80: 45970 | J80: 120.7 | K80: Followed up via email regarding outstanding invoice INV0002982.
A81: COL0001497 | B81: MER00140 | C81: INV0002982 | D81: 45976 | E81: Phone | F81: Phone | G81: Nandini Rajan | H81: No Response | K81: Called merchant to discuss overdue invoice INV0002982.
A82: COL0001498 | B82: MER00140 | C82: INV0002982 | D82: 45982 | E82: Escalation | F82: Phone | G82: Sanjay Kumar | H82: Escalated | K82: Escalated invoice INV0002982 to account manager for non-payment.
A83: COL0001499 | B83: MER00140 | C83: INV0002985 | D83: 46046 | E83: Reminder | F83: Email | G83: Manish Tiwari | H83: No Response | K83: Automated reminder sent for invoice INV0002985 due 2026-01-17.
A84: COL0001500 | B84: MER00140 | C84: INV0002985 | D84: 46057 | E84: Email | F84: Email | G84: Nandini Rajan | H84: No Response | K84: Followed up via email regarding outstanding invoice INV0002985.
A85: COL0001501 | B85: MER00140 | C85: INV0002985 | D85: 46067 | E85: Phone | F85: Phone | G85: Manish Tiwari | H85: Promise to Pay | I85: 46071 | J85: 388.51 | K85: Called merchant to discuss overdue invoice INV0002985.
A86: COL0001502 | B86: MER00140 | C86: INV0002985 | D86: 46078 | E86: Escalation | F86: Phone | G86: Nandini Rajan | H86: Disputed | K86: Escalated invoice INV0002985 to account manager for non-payment.
A87: COL0001503 | B87: MER00140 | C87: INV0002985 | D87: 46083 | E87: Payment Promise | F87: WhatsApp | G87: Nandini Rajan | H87: Promise to Pay | I87: 46086 | J87: 368.09 | K87: Merchant committed to paying invoice INV0002985 by 2026-03-05.
A88: COL0001504 | B88: MER00140 | C88: INV0002990 | D88: 46223 | E88: Reminder | F88: Email | G88: Sanjay Kumar | H88: Promise to Pay | I88: 46226 | J88: 474.59 | K88: Automated reminder sent for invoice INV0002990 due 2026-07-17.
A89: COL0001505 | B89: MER00140 | C89: INV0002990 | D89: 46235 | E89: Email | F89: Email | G89: Sanjay Kumar | H89: No Response | K89: Followed up via email regarding outstanding invoice INV0002990.
A90: COL0001506 | B90: MER00140 | C90: INV0002990 | D90: 46244 | E90: Phone | F90: Phone | G90: Nandini Rajan | H90: Disputed | K90: Called merchant to discuss overdue invoice INV0002990.
A91: COL0001507 | B91: MER00140 | C91: INV0002990 | D91: 46258 | E91: Escalation | F91: Phone | G91: Manish Tiwari | H91: Escalated | K91: Escalated invoice INV0002990 to account manager for non-payment.
A92: COL0001602 | B92: MER00156 | C92: INV0003311 | D92: 45907 | E92: Reminder | F92: Email | G92: Vivek Nair | H92: No Response | K92: Automated reminder sent for invoice INV0003311 due 2025-09-01.
A93: COL0001603 | B93: MER00156 | C93: INV0003311 | D93: 45916 | E93: Email | F93: Email | G93: Manish Tiwari | H93: No Response | K93: Followed up via email regarding outstanding invoice INV0003311.
A94: COL0001604 | B94: MER00156 | C94: INV0003311 | D94: 45923 | E94: Phone | F94: Phone | G94: Shweta Gupta | H94: Promise to Pay | I94: 45926 | J94: 200.03 | K94: Called merchant to discuss overdue invoice INV0003311.
A95: COL0001605 | B95: MER00156 | C95: INV0003313 | D95: 45966 | E95: Reminder | F95: Email | G95: Amit Saxena | H95: No Response | K95: Automated reminder sent for invoice INV0003313 due 2025-11-01.
A96: COL0001606 | B96: MER00156 | C96: INV0003313 | D96: 45977 | E96: Email | F96: Email | G96: Amit Saxena | H96: Disputed | K96: Followed up via email regarding outstanding invoice INV0003313.
A97: COL0001607 | B97: MER00156 | C97: INV0003313 | D97: 45985 | E97: Phone | F97: Phone | G97: Anjali Desai | H97: No Response | K97: Called merchant to discuss overdue invoice INV0003313.
A98: COL0001608 | B98: MER00156 | C98: INV0003314 | D98: 45996 | E98: Reminder | F98: Email | G98: Vivek Nair | H98: Promise to Pay | I98: 46006 | J98: 136.44 | K98: Automated reminder sent for invoice INV0003314 due 2025-12-02.
A99: COL0001609 | B99: MER00156 | C99: INV0003314 | D99: 46009 | E99: Email | F99: Email | G99: Nandini Rajan | H99: No Response | K99: Followed up via email regarding outstanding invoice INV0003314.
A100: COL0001610 | B100: MER00156 | C100: INV0003314 | D100: 46017 | E100: Phone | F100: Phone | G100: Vivek Nair | H100: Promise to Pay | I100: 46030 | J100: 136.88 | K100: Called merchant to discuss overdue invoice INV0003314.
A101: COL0001611 | B101: MER00156 | C101: INV0003318 | D101: 46119 | E101: Reminder | F101: Email | G101: Ritu Bansal | H101: No Response | K101: Automated reminder sent for invoice INV0003318 due 2026-04-01.
...

Sheet Revenue Reconciliation
A1: Revenue Reconciliation - invoice vs. total payments, status via IFS
A3: invoice_id | B3: merchant_id | C3: total_invoice_amount | D3: total_paid | E3: variance | F3: reconciliation_status
A4: INV0000956 | B4: MER00048 | C4: =XLOOKUP(A4,tblInvoices[invoice_id],tblInvoices[total_invoice_amount]) | D4: =SUMIFS(tblPayments[payment_amount],tblPayments[invoice_id],A4,tblPayments[payment_status],"Success") | E4: =D4-C4 | F4: =IFS(D4=0,"MISSING_PAYMENT",ABS(E4)<=1,"MATCHED",E4>1,"AMOUNT_MISMATCH",TRUE,"PARTIAL")
A5: INV0000957 | B5: MER00048 | C5: =XLOOKUP(A5,tblInvoices[invoice_id],tblInvoices[total_invoice_amount]) | D5: =SUMIFS(tblPayments[payment_amount],tblPayments[invoice_id],A5,tblPayments[payment_status],"Success") | E5: =D5-C5 | F5: =IFS(D5=0,"MISSING_PAYMENT",ABS(E5)<=1,"MATCHED",E5>1,"AMOUNT_MISMATCH",TRUE,"PARTIAL")
A6: INV0000958 | B6: MER00048 | C6: =XLOOKUP(A6,tblInvoices[invoice_id],tblInvoices[total_invoice_amount]) | D6: =SUMIFS(tblPayments[payment_amount],tblPayments[invoice_id],A6,tblPayments[payment_status],"Success") | E6: =D6-C6 | F6: =IFS(D6=0,"MISSING_PAYMENT",ABS(E6)<=1,"MATCHED",E6>1,"AMOUNT_MISMATCH",TRUE,"PARTIAL")
A7: INV0000959 | B7: MER00048 | C7: =XLOOKUP(A7,tblInvoices[invoice_id],tblInvoices[total_invoice_amount]) | D7: =SUMIFS(tblPayments[payment_amount],tblPayments[invoice_id],A7,tblPayments[payment_status],"Success") | E7: =D7-C7 | F7: =IFS(D7=0,"MISSING_PAYMENT",ABS(E7)<=1,"MATCHED",E7>1,"AMOUNT_MISMATCH",TRUE,"PARTIAL")
A8: INV0000960 | B8: MER00048 | C8: =XLOOKUP(A8,tblInvoices[invoice_id],tblInvoices[total_invoice_amount]) | D8: =SUMIFS(tblPayments[payment_amount],tblPayments[invoice_id],A8,tblPayments[payment_status],"Success") | E8: =D8-C8 | F8: =IFS(D8=0,"MISSING_PAYMENT",ABS(E8)<=1,"MATCHED",E8>1,"AMOUNT_MISMATCH",TRUE,"PARTIAL")
A9: INV0000961 | B9: MER00048 | C9: =XLOOKUP(A9,tblInvoices[invoice_id],tblInvoices[total_invoice_amount]) | D9: =SUMIFS(tblPayments[payment_amount],tblPayments[invoice_id],A9,tblPayments[payment_status],"Success") | E9: =D9-C9 | F9: =IFS(D9=0,"MISSING_PAYMENT",ABS(E9)<=1,"MATCHED",E9>1,"AMOUNT_MISMATCH",TRUE,"PARTIAL")
A10: INV0000962 | B10: MER00048 | C10: =XLOOKUP(A10,tblInvoices[invoice_id],tblInvoices[total_invoice_amount]) | D10: =SUMIFS(tblPayments[payment_amount],tblPayments[invoice_id],A10,tblPayments[payment_status],"Success") | E10: =D10-C10 | F10: =IFS(D10=0,"MISSING_PAYMENT",ABS(E10)<=1,"MATCHED",E10>1,"AMOUNT_MISMATCH",TRUE,"PARTIAL")
A11: INV0000963 | B11: MER00048 | C11: =XLOOKUP(A11,tblInvoices[invoice_id],tblInvoices[total_invoice_amount]) | D11: =SUMIFS(tblPayments[payment_amount],tblPayments[invoice_id],A11,tblPayments[payment_status],"Success") | E11: =D11-C11 | F11: =IFS(D11=0,"MISSING_PAYMENT",ABS(E11)<=1,"MATCHED",E11>1,"AMOUNT_MISMATCH",TRUE,"PARTIAL")
A12: INV0000964 | B12: MER00048 | C12: =XLOOKUP(A12,tblInvoices[invoice_id],tblInvoices[total_invoice_amount]) | D12: =SUMIFS(tblPayments[payment_amount],tblPayments[invoice_id],A12,tblPayments[payment_status],"Success") | E12: =D12-C12 | F12: =IFS(D12=0,"MISSING_PAYMENT",ABS(E12)<=1,"MATCHED",E12>1,"AMOUNT_MISMATCH",TRUE,"PARTIAL")
A13: INV0000965 | B13: MER00048 | C13: =XLOOKUP(A13,tblInvoices[invoice_id],tblInvoices[total_invoice_amount]) | D13: =SUMIFS(tblPayments[payment_amount],tblPayments[invoice_id],A13,tblPayments[payment_status],"Success") | E13: =D13-C13 | F13: =IFS(D13=0,"MISSING_PAYMENT",ABS(E13)<=1,"MATCHED",E13>1,"AMOUNT_MISMATCH",TRUE,"PARTIAL")
A14: INV0000966 | B14: MER00048 | C14: =XLOOKUP(A14,tblInvoices[invoice_id],tblInvoices[total_invoice_amount]) | D14: =SUMIFS(tblPayments[payment_amount],tblPayments[invoice_id],A14,tblPayments[payment_status],"Success") | E14: =D14-C14 | F14: =IFS(D14=0,"MISSING_PAYMENT",ABS(E14)<=1,"MATCHED",E14>1,"AMOUNT_MISMATCH",TRUE,"PARTIAL")
A15: INV0000967 | B15: MER00048 | C15: =XLOOKUP(A15,tblInvoices[invoice_id],tblInvoices[total_invoice_amount]) | D15: =SUMIFS(tblPayments[payment_amount],tblPayments[invoice_id],A15,tblPayments[payment_status],"Success") | E15: =D15-C15 | F15: =IFS(D15=0,"MISSING_PAYMENT",ABS(E15)<=1,"MATCHED",E15>1,"AMOUNT_MISMATCH",TRUE,"PARTIAL")
... A898: INV0019140 | B898: MER00902 | C898: =XLOOKUP(A898,tblInvoices[invoice_id],tblInvoices[total_invoice_amount]) | D898: =SUMIFS(tblPayments[payment_amount],tblPayments[invoice_id],A898,tblPayments[payment_status],"Success") | E898: =D898-C898 | F898: =IFS(D898=0,"MISSING_PAYMENT",ABS(E898)<=1,"MATCHED",E898>1,"AMOUNT_MISMATCH",TRUE,"PARTIAL")

Sheet Monthly MIS
A1: Monthly MIS - billed revenue and invoice counts via SUMIFS/COUNTIFS on Invoices
A3: billing_period_start_month | B3: invoice_count | C3: expected_revenue | D3: billed_revenue | E3: revenue_variance | F3: period_start (helper) | G3: period_end (helper)
A4: 2024-08 | B4: =COUNTIFS(tblInvoices[billing_period_start],">="&F4,tblInvoices[billing_period_start],"<"&G4) | C4: =SUMIFS(tblInvoices[expected_fee],tblInvoices[billing_period_start],">="&F4,tblInvoices[billing_period_start],"<"&G4) | D4: =SUMIFS(tblInvoices[billed_fee],tblInvoices[billing_period_start],">="&F4,tblInvoices[billing_period_start],"<"&G4) | E4: =D4-C4 | F4: =DATE(VALUE(LEFT(A4,4)),VALUE(MID(A4,6,2)),1) | G4: =EDATE(F4,1)
A5: 2024-09 | B5: =COUNTIFS(tblInvoices[billing_period_start],">="&F5,tblInvoices[billing_period_start],"<"&G5) | C5: =SUMIFS(tblInvoices[expected_fee],tblInvoices[billing_period_start],">="&F5,tblInvoices[billing_period_start],"<"&G5) | D5: =SUMIFS(tblInvoices[billed_fee],tblInvoices[billing_period_start],">="&F5,tblInvoices[billing_period_start],"<"&G5) | E5: =D5-C5 | F5: =DATE(VALUE(LEFT(A5,4)),VALUE(MID(A5,6,2)),1) | G5: =EDATE(F5,1)
A6: 2024-10 | B6: =COUNTIFS(tblInvoices[billing_period_start],">="&F6,tblInvoices[billing_period_start],"<"&G6) | C6: =SUMIFS(tblInvoices[expected_fee],tblInvoices[billing_period_start],">="&F6,tblInvoices[billing_period_start],"<"&G6) | D6: =SUMIFS(tblInvoices[billed_fee],tblInvoices[billing_period_start],">="&F6,tblInvoices[billing_period_start],"<"&G6) | E6: =D6-C6 | F6: =DATE(VALUE(LEFT(A6,4)),VALUE(MID(A6,6,2)),1) | G6: =EDATE(F6,1)
A7: 2024-11 | B7: =COUNTIFS(tblInvoices[billing_period_start],">="&F7,tblInvoices[billing_period_start],"<"&G7) | C7: =SUMIFS(tblInvoices[expected_fee],tblInvoices[billing_period_start],">="&F7,tblInvoices[billing_period_start],"<"&G7) | D7: =SUMIFS(tblInvoices[billed_fee],tblInvoices[billing_period_start],">="&F7,tblInvoices[billing_period_start],"<"&G7) | E7: =D7-C7 | F7: =DATE(VALUE(LEFT(A7,4)),VALUE(MID(A7,6,2)),1) | G7: =EDATE(F7,1)
A8: 2024-12 | B8: =COUNTIFS(tblInvoices[billing_period_start],">="&F8,tblInvoices[billing_period_start],"<"&G8) | C8: =SUMIFS(tblInvoices[expected_fee],tblInvoices[billing_period_start],">="&F8,tblInvoices[billing_period_start],"<"&G8) | D8: =SUMIFS(tblInvoices[billed_fee],tblInvoices[billing_period_start],">="&F8,tblInvoices[billing_period_start],"<"&G8) | E8: =D8-C8 | F8: =DATE(VALUE(LEFT(A8,4)),VALUE(MID(A8,6,2)),1) | G8: =EDATE(F8,1)
A9: 2025-01 | B9: =COUNTIFS(tblInvoices[billing_period_start],">="&F9,tblInvoices[billing_period_start],"<"&G9) | C9: =SUMIFS(tblInvoices[expected_fee],tblInvoices[billing_period_start],">="&F9,tblInvoices[billing_period_start],"<"&G9) | D9: =SUMIFS(tblInvoices[billed_fee],tblInvoices[billing_period_start],">="&F9,tblInvoices[billing_period_start],"<"&G9) | E9: =D9-C9 | F9: =DATE(VALUE(LEFT(A9,4)),VALUE(MID(A9,6,2)),1) | G9: =EDATE(F9,1)
A10: 2025-02 | B10: =COUNTIFS(tblInvoices[billing_period_start],">="&F10,tblInvoices[billing_period_start],"<"&G10) | C10: =SUMIFS(tblInvoices[expected_fee],tblInvoices[billing_period_start],">="&F10,tblInvoices[billing_period_start],"<"&G10) | D10: =SUMIFS(tblInvoices[billed_fee],tblInvoices[billing_period_start],">="&F10,tblInvoices[billing_period_start],"<"&G10) | E10: =D10-C10 | F10: =DATE(VALUE(LEFT(A10,4)),VALUE(MID(A10,6,2)),1) | G10: =EDATE(F10,1)
A11: 2025-03 | B11: =COUNTIFS(tblInvoices[billing_period_start],">="&F11,tblInvoices[billing_period_start],"<"&G11) | C11: =SUMIFS(tblInvoices[expected_fee],tblInvoices[billing_period_start],">="&F11,tblInvoices[billing_period_start],"<"&G11) | D11: =SUMIFS(tblInvoices[billed_fee],tblInvoices[billing_period_start],">="&F11,tblInvoices[billing_period_start],"<"&G11) | E11: =D11-C11 | F11: =DATE(VALUE(LEFT(A11,4)),VALUE(MID(A11,6,2)),1) | G11: =EDATE(F11,1)
A12: 2025-04 | B12: =COUNTIFS(tblInvoices[billing_period_start],">="&F12,tblInvoices[billing_period_start],"<"&G12) | C12: =SUMIFS(tblInvoices[expected_fee],tblInvoices[billing_period_start],">="&F12,tblInvoices[billing_period_start],"<"&G12) | D12: =SUMIFS(tblInvoices[billed_fee],tblInvoices[billing_period_start],">="&F12,tblInvoices[billing_period_start],"<"&G12) | E12: =D12-C12 | F12: =DATE(VALUE(LEFT(A12,4)),VALUE(MID(A12,6,2)),1) | G12: =EDATE(F12,1)
A13: 2025-05 | B13: =COUNTIFS(tblInvoices[billing_period_start],">="&F13,tblInvoices[billing_period_start],"<"&G13) | C13: =SUMIFS(tblInvoices[expected_fee],tblInvoices[billing_period_start],">="&F13,tblInvoices[billing_period_start],"<"&G13) | D13: =SUMIFS(tblInvoices[billed_fee],tblInvoices[billing_period_start],">="&F13,tblInvoices[billing_period_start],"<"&G13) | E13: =D13-C13 | F13: =DATE(VALUE(LEFT(A13,4)),VALUE(MID(A13,6,2)),1) | G13: =EDATE(F13,1)
A14: 2025-06 | B14: =COUNTIFS(tblInvoices[billing_period_start],">="&F14,tblInvoices[billing_period_start],"<"&G14) | C14: =SUMIFS(tblInvoices[expected_fee],tblInvoices[billing_period_start],">="&F14,tblInvoices[billing_period_start],"<"&G14) | D14: =SUMIFS(tblInvoices[billed_fee],tblInvoices[billing_period_start],">="&F14,tblInvoices[billing_period_start],"<"&G14) | E14: =D14-C14 | F14: =DATE(VALUE(LEFT(A14,4)),VALUE(MID(A14,6,2)),1) | G14: =EDATE(F14,1)
A15: 2025-07 | B15: =COUNTIFS(tblInvoices[billing_period_start],">="&F15,tblInvoices[billing_period_start],"<"&G15) | C15: =SUMIFS(tblInvoices[expected_fee],tblInvoices[billing_period_start],">="&F15,tblInvoices[billing_period_start],"<"&G15) | D15: =SUMIFS(tblInvoices[billed_fee],tblInvoices[billing_period_start],">="&F15,tblInvoices[billing_period_start],"<"&G15) | E15: =D15-C15 | F15: =DATE(VALUE(LEFT(A15,4)),VALUE(MID(A15,6,2)),1) | G15: =EDATE(F15,1)
... A27: 2026-07 | B27: =COUNTIFS(tblInvoices[billing_period_start],">="&F27,tblInvoices[billing_period_start],"<"&G27) | C27: =SUMIFS(tblInvoices[expected_fee],tblInvoices[billing_period_start],">="&F27,tblInvoices[billing_period_start],"<"&G27) | D27: =SUMIFS(tblInvoices[billed_fee],tblInvoices[billing_period_start],">="&F27,tblInvoices[billing_period_start],"<"&G27) | E27: =D27-C27 | F27: =DATE(VALUE(LEFT(A27,4)),VALUE(MID(A27,6,2)),1) | G27: =EDATE(F27,1)
